{
    "org.jsoup.Connection.Method#<clinit>": 0.0,
    "org.jsoup.Connection.Method#Connection$Method": 0.0,
    "org.jsoup.Jsoup#Jsoup": 0,
    "org.jsoup.Jsoup#clean": 0.0,
    "org.jsoup.Jsoup#connect": 0.0,
    "org.jsoup.Jsoup#isValid": 0.0,
    "org.jsoup.Jsoup#parse": 0.1111111111111111,
    "org.jsoup.Jsoup#parseBodyFragment": 0.0,
    "org.jsoup.helper.DataUtil#<clinit>": 0.23904572186687872,
    "org.jsoup.helper.DataUtil#DataUtil": 0,
    "org.jsoup.helper.DataUtil#getCharsetFromContentType": 0.0,
    "org.jsoup.helper.DataUtil#load": 0.0,
    "org.jsoup.helper.DataUtil#parseByteData": 0.2581988897471611,
    "org.jsoup.helper.DataUtil#readToByteBuffer": 0.26967994498529685,
    "org.jsoup.helper.DescendableLinkedList#DescendableLinkedList": 0.2324691725103883,
    "org.jsoup.helper.DescendableLinkedList#descendingIterator": 0.22207522631609475,
    "org.jsoup.helper.DescendableLinkedList#peekLast": 0.2083022575693182,
    "org.jsoup.helper.DescendableLinkedList#pollLast": 0.2083022575693182,
    "org.jsoup.helper.DescendableLinkedList#push": 0.03296902366978935,
    "org.jsoup.helper.DescendableLinkedList.DescendingIterator#DescendableLinkedList$DescendingIterator": 0.22207522631609475,
    "org.jsoup.helper.DescendableLinkedList.DescendingIterator#hasNext": 0.22207522631609475,
    "org.jsoup.helper.DescendableLinkedList.DescendingIterator#next": 0.22245516710084084,
    "org.jsoup.helper.DescendableLinkedList.DescendingIterator#remove": 0.21653278478430668,
    "org.jsoup.helper.HttpConnection#HttpConnection": 0.0,
    "org.jsoup.helper.HttpConnection#connect": 0.0,
    "org.jsoup.helper.HttpConnection#cookie": 0.0,
    "org.jsoup.helper.HttpConnection#cookies": 0,
    "org.jsoup.helper.HttpConnection#data": 0.0,
    "org.jsoup.helper.HttpConnection#execute": 0,
    "org.jsoup.helper.HttpConnection#followRedirects": 0,
    "org.jsoup.helper.HttpConnection#get": 0,
    "org.jsoup.helper.HttpConnection#header": 0,
    "org.jsoup.helper.HttpConnection#ignoreContentType": 0,
    "org.jsoup.helper.HttpConnection#ignoreHttpErrors": 0,
    "org.jsoup.helper.HttpConnection#maxBodySize": 0,
    "org.jsoup.helper.HttpConnection#method": 0.0,
    "org.jsoup.helper.HttpConnection#parser": 0,
    "org.jsoup.helper.HttpConnection#post": 0,
    "org.jsoup.helper.HttpConnection#referrer": 0.0,
    "org.jsoup.helper.HttpConnection#request": 0,
    "org.jsoup.helper.HttpConnection#response": 0,
    "org.jsoup.helper.HttpConnection#setSecure": 0,
    "org.jsoup.helper.HttpConnection#timeout": 0.0,
    "org.jsoup.helper.HttpConnection#url": 0.0,
    "org.jsoup.helper.HttpConnection#userAgent": 0.0,
    "org.jsoup.helper.HttpConnection.Base#HttpConnection$Base": 0.0,
    "org.jsoup.helper.HttpConnection.Base#cookie": 0.0,
    "org.jsoup.helper.HttpConnection.Base#cookies": 0.0,
    "org.jsoup.helper.HttpConnection.Base#getHeaderCaseInsensitive": 0.0,
    "org.jsoup.helper.HttpConnection.Base#hasCookie": 0,
    "org.jsoup.helper.HttpConnection.Base#hasHeader": 0.0,
    "org.jsoup.helper.HttpConnection.Base#header": 0.0,
    "org.jsoup.helper.HttpConnection.Base#headers": 0.0,
    "org.jsoup.helper.HttpConnection.Base#method": 0.0,
    "org.jsoup.helper.HttpConnection.Base#removeCookie": 0,
    "org.jsoup.helper.HttpConnection.Base#removeHeader": 0.0,
    "org.jsoup.helper.HttpConnection.Base#scanHeaders": 0.0,
    "org.jsoup.helper.HttpConnection.Base#url": 0.0,
    "org.jsoup.helper.HttpConnection.KeyVal#HttpConnection$KeyVal": 0.0,
    "org.jsoup.helper.HttpConnection.KeyVal#create": 0.0,
    "org.jsoup.helper.HttpConnection.KeyVal#key": 0.0,
    "org.jsoup.helper.HttpConnection.KeyVal#toString": 0.0,
    "org.jsoup.helper.HttpConnection.KeyVal#value": 0.0,
    "org.jsoup.helper.HttpConnection.Request#HttpConnection$Request": 0.0,
    "org.jsoup.helper.HttpConnection.Request#data": 0.0,
    "org.jsoup.helper.HttpConnection.Request#followRedirects": 0,
    "org.jsoup.helper.HttpConnection.Request#ignoreContentType": 0,
    "org.jsoup.helper.HttpConnection.Request#ignoreHttpErrors": 0,
    "org.jsoup.helper.HttpConnection.Request#isSecure": 0,
    "org.jsoup.helper.HttpConnection.Request#maxBodySize": 0,
    "org.jsoup.helper.HttpConnection.Request#parser": 0,
    "org.jsoup.helper.HttpConnection.Request#setSecure": 0,
    "org.jsoup.helper.HttpConnection.Request#timeout": 0.0,
    "org.jsoup.helper.HttpConnection.Response#HttpConnection$Response": 0,
    "org.jsoup.helper.HttpConnection.Response#body": 0,
    "org.jsoup.helper.HttpConnection.Response#bodyAsBytes": 0,
    "org.jsoup.helper.HttpConnection.Response#charset": 0,
    "org.jsoup.helper.HttpConnection.Response#contentType": 0,
    "org.jsoup.helper.HttpConnection.Response#createConnection": 0,
    "org.jsoup.helper.HttpConnection.Response#execute": 0,
    "org.jsoup.helper.HttpConnection.Response#getRequestCookieString": 0,
    "org.jsoup.helper.HttpConnection.Response#initUnSecureSSL": 0,
    "org.jsoup.helper.HttpConnection.Response#parse": 0,
    "org.jsoup.helper.HttpConnection.Response#processResponseHeaders": 0.0,
    "org.jsoup.helper.HttpConnection.Response#serialiseRequestUrl": 0,
    "org.jsoup.helper.HttpConnection.Response#setupFromConnection": 0,
    "org.jsoup.helper.HttpConnection.Response#statusCode": 0,
    "org.jsoup.helper.HttpConnection.Response#statusMessage": 0,
    "org.jsoup.helper.HttpConnection.Response#writePost": 0,
    "org.jsoup.helper.StringUtil#<clinit>": 0.23352028189084703,
    "org.jsoup.helper.StringUtil#StringUtil": 0,
    "org.jsoup.helper.StringUtil#in": 0.21555282996991385,
    "org.jsoup.helper.StringUtil#isBlank": 0.0,
    "org.jsoup.helper.StringUtil#isNumeric": 0.0,
    "org.jsoup.helper.StringUtil#isWhitespace": 0.22896983309165297,
    "org.jsoup.helper.StringUtil#join": 0.0,
    "org.jsoup.helper.StringUtil#normaliseWhitespace": 0.18973665961010278,
    "org.jsoup.helper.StringUtil#padding": 0.0,
    "org.jsoup.helper.Validate#Validate": 0,
    "org.jsoup.helper.Validate#fail": 0,
    "org.jsoup.helper.Validate#isFalse": 0.23676127348263276,
    "org.jsoup.helper.Validate#isTrue": 0.1685499656158105,
    "org.jsoup.helper.Validate#noNullElements": 0.0,
    "org.jsoup.helper.Validate#notEmpty": 0.10112997936948631,
    "org.jsoup.helper.Validate#notNull": 0.23212194427697994,
    "org.jsoup.nodes.Attribute#Attribute": 0.24343224778007383,
    "org.jsoup.nodes.Attribute#clone": 0,
    "org.jsoup.nodes.Attribute#createFromEncoded": 0,
    "org.jsoup.nodes.Attribute#equals": 0.0,
    "org.jsoup.nodes.Attribute#getKey": 0.24456713620629725,
    "org.jsoup.nodes.Attribute#getValue": 0.1751423610260147,
    "org.jsoup.nodes.Attribute#hashCode": 0.0,
    "org.jsoup.nodes.Attribute#html": 0.13968605915391563,
    "org.jsoup.nodes.Attribute#isDataAttribute": 0.0,
    "org.jsoup.nodes.Attribute#setKey": 0,
    "org.jsoup.nodes.Attribute#setValue": 0.07453559924999299,
    "org.jsoup.nodes.Attribute#toString": 0.0,
    "org.jsoup.nodes.Attributes#Attributes": 0.23352028189084703,
    "org.jsoup.nodes.Attributes#addAll": 0.0,
    "org.jsoup.nodes.Attributes#asList": 0.05423261445466404,
    "org.jsoup.nodes.Attributes#clone": 0.0,
    "org.jsoup.nodes.Attributes#dataKey": 0.0,
    "org.jsoup.nodes.Attributes#dataset": 0.0,
    "org.jsoup.nodes.Attributes#equals": 0.0,
    "org.jsoup.nodes.Attributes#get": 0.1751423610260147,
    "org.jsoup.nodes.Attributes#hasKey": 0.2021840210757971,
    "org.jsoup.nodes.Attributes#hashCode": 0.0,
    "org.jsoup.nodes.Attributes#html": 0.13968605915391563,
    "org.jsoup.nodes.Attributes#iterator": 0.043852900965351466,
    "org.jsoup.nodes.Attributes#put": 0.24456713620629725,
    "org.jsoup.nodes.Attributes#remove": 0.0,
    "org.jsoup.nodes.Attributes#size": 0.0,
    "org.jsoup.nodes.Attributes#toString": 0.0,
    "org.jsoup.nodes.Attributes.Dataset#Attributes$Dataset": 0.0,
    "org.jsoup.nodes.Attributes.Dataset#entrySet": 0.0,
    "org.jsoup.nodes.Attributes.Dataset#put": 0.0,
    "org.jsoup.nodes.Attributes.Dataset.DatasetIterator#Attributes$Dataset$DatasetIterator": 0.0,
    "org.jsoup.nodes.Attributes.Dataset.DatasetIterator#hasNext": 0.0,
    "org.jsoup.nodes.Attributes.Dataset.DatasetIterator#next": 0.0,
    "org.jsoup.nodes.Attributes.Dataset.DatasetIterator#remove": 0.0,
    "org.jsoup.nodes.Attributes.Dataset.EntrySet#Attributes$Dataset$EntrySet": 0.0,
    "org.jsoup.nodes.Attributes.Dataset.EntrySet#iterator": 0.0,
    "org.jsoup.nodes.Attributes.Dataset.EntrySet#size": 0.0,
    "org.jsoup.nodes.Comment#Comment": 0.18136906252750293,
    "org.jsoup.nodes.Comment#getData": 0.06454972243679027,
    "org.jsoup.nodes.Comment#nodeName": 0.07071067811865475,
    "org.jsoup.nodes.Comment#outerHtmlHead": 0.07071067811865475,
    "org.jsoup.nodes.Comment#outerHtmlTail": 0.07071067811865475,
    "org.jsoup.nodes.Comment#toString": 0,
    "org.jsoup.nodes.DataNode#DataNode": 0.21081851067789195,
    "org.jsoup.nodes.DataNode#createFromEncoded": 0,
    "org.jsoup.nodes.DataNode#getWholeData": 0.0,
    "org.jsoup.nodes.DataNode#nodeName": 0.0,
    "org.jsoup.nodes.DataNode#outerHtmlHead": 0.0,
    "org.jsoup.nodes.DataNode#outerHtmlTail": 0.0,
    "org.jsoup.nodes.DataNode#setWholeData": 0,
    "org.jsoup.nodes.DataNode#toString": 0,
    "org.jsoup.nodes.Document#Document": 0.23530426719358322,
    "org.jsoup.nodes.Document#body": 0.1355261854357877,
    "org.jsoup.nodes.Document#clone": 0.0,
    "org.jsoup.nodes.Document#createElement": 0.0,
    "org.jsoup.nodes.Document#createShell": 0.043852900965351466,
    "org.jsoup.nodes.Document#findFirstElementByTagName": 0.1355261854357877,
    "org.jsoup.nodes.Document#head": 0.0,
    "org.jsoup.nodes.Document#nodeName": 0.13219579477176954,
    "org.jsoup.nodes.Document#normalise": 0,
    "org.jsoup.nodes.Document#normaliseStructure": 0,
    "org.jsoup.nodes.Document#normaliseTextNodes": 0,
    "org.jsoup.nodes.Document#outerHtml": 0.0,
    "org.jsoup.nodes.Document#outputSettings": 0.0,
    "org.jsoup.nodes.Document#quirksMode": 0.03333333333333333,
    "org.jsoup.nodes.Document#text": 0.0,
    "org.jsoup.nodes.Document#title": 0.0,
    "org.jsoup.nodes.Document.OutputSettings#Document$OutputSettings": 0.23530426719358322,
    "org.jsoup.nodes.Document.OutputSettings#charset": 0.23094010767585027,
    "org.jsoup.nodes.Document.OutputSettings#clone": 0.0,
    "org.jsoup.nodes.Document.OutputSettings#encoder": 0.13324272283470417,
    "org.jsoup.nodes.Document.OutputSettings#escapeMode": 0.0,
    "org.jsoup.nodes.Document.OutputSettings#indentAmount": 0.0,
    "org.jsoup.nodes.Document.OutputSettings#outline": 0.0,
    "org.jsoup.nodes.Document.OutputSettings#prettyPrint": 0.0,
    "org.jsoup.nodes.Document.QuirksMode#<clinit>": 0.23530426719358322,
    "org.jsoup.nodes.Document.QuirksMode#Document$QuirksMode": 0.23530426719358322,
    "org.jsoup.nodes.DocumentType#DocumentType": 0.28867513459481287,
    "org.jsoup.nodes.DocumentType#nodeName": 0.09128709291752768,
    "org.jsoup.nodes.DocumentType#outerHtmlHead": 0.09128709291752768,
    "org.jsoup.nodes.DocumentType#outerHtmlTail": 0.09128709291752768,
    "org.jsoup.nodes.Element#Element": 0.23494419924401153,
    "org.jsoup.nodes.Element#accumulateParents": 0.03227486121839514,
    "org.jsoup.nodes.Element#addClass": 0.0,
    "org.jsoup.nodes.Element#after": 0.0,
    "org.jsoup.nodes.Element#append": 0.0,
    "org.jsoup.nodes.Element#appendChild": 0.23676127348263276,
    "org.jsoup.nodes.Element#appendElement": 0.042257712736425826,
    "org.jsoup.nodes.Element#appendNormalisedText": 0.1623086135160589,
    "org.jsoup.nodes.Element#appendText": 0.0,
    "org.jsoup.nodes.Element#appendWhitespaceIfBr": 0.0,
    "org.jsoup.nodes.Element#attr": 0.0,
    "org.jsoup.nodes.Element#before": 0.0,
    "org.jsoup.nodes.Element#child": 0.14907119849998599,
    "org.jsoup.nodes.Element#children": 0.09583148474999098,
    "org.jsoup.nodes.Element#className": 0.09128709291752768,
    "org.jsoup.nodes.Element#classNames": 0.0,
    "org.jsoup.nodes.Element#clone": 0.0,
    "org.jsoup.nodes.Element#data": 0.0,
    "org.jsoup.nodes.Element#dataNodes": 0.0,
    "org.jsoup.nodes.Element#dataset": 0.0,
    "org.jsoup.nodes.Element#elementSiblingIndex": 0.0,
    "org.jsoup.nodes.Element#empty": 0.0,
    "org.jsoup.nodes.Element#equals": 0.0,
    "org.jsoup.nodes.Element#firstElementSibling": 0.0,
    "org.jsoup.nodes.Element#getAllElements": 0.0,
    "org.jsoup.nodes.Element#getElementById": 0.0,
    "org.jsoup.nodes.Element#getElementsByAttribute": 0.0,
    "org.jsoup.nodes.Element#getElementsByAttributeStarting": 0,
    "org.jsoup.nodes.Element#getElementsByAttributeValue": 0.0,
    "org.jsoup.nodes.Element#getElementsByAttributeValueContaining": 0,
    "org.jsoup.nodes.Element#getElementsByAttributeValueEnding": 0,
    "org.jsoup.nodes.Element#getElementsByAttributeValueMatching": 0,
    "org.jsoup.nodes.Element#getElementsByAttributeValueNot": 0,
    "org.jsoup.nodes.Element#getElementsByAttributeValueStarting": 0,
    "org.jsoup.nodes.Element#getElementsByClass": 0.0,
    "org.jsoup.nodes.Element#getElementsByIndexEquals": 0,
    "org.jsoup.nodes.Element#getElementsByIndexGreaterThan": 0,
    "org.jsoup.nodes.Element#getElementsByIndexLessThan": 0,
    "org.jsoup.nodes.Element#getElementsByTag": 0.14638501094227999,
    "org.jsoup.nodes.Element#getElementsContainingOwnText": 0,
    "org.jsoup.nodes.Element#getElementsContainingText": 0,
    "org.jsoup.nodes.Element#getElementsMatchingOwnText": 0,
    "org.jsoup.nodes.Element#getElementsMatchingText": 0,
    "org.jsoup.nodes.Element#hasClass": 0.10540925533894598,
    "org.jsoup.nodes.Element#hasText": 0.0,
    "org.jsoup.nodes.Element#hashCode": 0.0,
    "org.jsoup.nodes.Element#html": 0.0,
    "org.jsoup.nodes.Element#id": 0.05679618342470648,
    "org.jsoup.nodes.Element#indexInList": 0,
    "org.jsoup.nodes.Element#insertChildren": 0.0,
    "org.jsoup.nodes.Element#isBlock": 0.11180339887498948,
    "org.jsoup.nodes.Element#lastElementSibling": 0.0,
    "org.jsoup.nodes.Element#nextElementSibling": 0,
    "org.jsoup.nodes.Element#nodeName": 0.23676127348263276,
    "org.jsoup.nodes.Element#outerHtmlHead": 0.13521679662509475,
    "org.jsoup.nodes.Element#outerHtmlTail": 0.13521679662509475,
    "org.jsoup.nodes.Element#ownText": 0.0,
    "org.jsoup.nodes.Element#parent": 0.16510016510024766,
    "org.jsoup.nodes.Element#parents": 0.03227486121839514,
    "org.jsoup.nodes.Element#prepend": 0.0,
    "org.jsoup.nodes.Element#prependChild": 0.0,
    "org.jsoup.nodes.Element#prependElement": 0.0,
    "org.jsoup.nodes.Element#prependText": 0.0,
    "org.jsoup.nodes.Element#preserveWhitespace": 0,
    "org.jsoup.nodes.Element#previousElementSibling": 0.0,
    "org.jsoup.nodes.Element#removeClass": 0.0,
    "org.jsoup.nodes.Element#select": 0.12777531299998798,
    "org.jsoup.nodes.Element#siblingElements": 0.0,
    "org.jsoup.nodes.Element#tag": 0.225,
    "org.jsoup.nodes.Element#tagName": 0.0,
    "org.jsoup.nodes.Element#text": 0.0,
    "org.jsoup.nodes.Element#textNodes": 0.0,
    "org.jsoup.nodes.Element#toString": 0.0,
    "org.jsoup.nodes.Element#toggleClass": 0.0,
    "org.jsoup.nodes.Element#val": 0.0,
    "org.jsoup.nodes.Element#wrap": 0.0,
    "org.jsoup.nodes.Element.1#head": 0.17610411189931965,
    "org.jsoup.nodes.Element.1#tail": 0.17610411189931965,
    "org.jsoup.nodes.Entities#<clinit>": 0.2328179636630391,
    "org.jsoup.nodes.Entities#Entities": 0,
    "org.jsoup.nodes.Entities#escape": 0.13181762600207414,
    "org.jsoup.nodes.Entities#getCharacterByName": 0.19069251784911848,
    "org.jsoup.nodes.Entities#isBaseNamedEntity": 0.2958039891549808,
    "org.jsoup.nodes.Entities#isNamedEntity": 0.35,
    "org.jsoup.nodes.Entities#loadEntities": 0.2328179636630391,
    "org.jsoup.nodes.Entities#toCharacterKey": 0.2328179636630391,
    "org.jsoup.nodes.Entities#unescape": 0.0,
    "org.jsoup.nodes.Entities.EscapeMode#<clinit>": 0.23422899454273052,
    "org.jsoup.nodes.Entities.EscapeMode#Entities$EscapeMode": 0.23422899454273052,
    "org.jsoup.nodes.Entities.EscapeMode#getMap": 0.13181762600207414,
    "org.jsoup.nodes.FormElement#FormElement": 0.2711630722733202,
    "org.jsoup.nodes.FormElement#addElement": 0.2711630722733202,
    "org.jsoup.nodes.FormElement#elements": 0.1,
    "org.jsoup.nodes.FormElement#formData": 0.0,
    "org.jsoup.nodes.FormElement#submit": 0.0,
    "org.jsoup.nodes.Node#Node": 0.2440467650459882,
    "org.jsoup.nodes.Node#absUrl": 0.06741998624632421,
    "org.jsoup.nodes.Node#addChildren": 0.0,
    "org.jsoup.nodes.Node#addSiblingHtml": 0.0,
    "org.jsoup.nodes.Node#after": 0.0,
    "org.jsoup.nodes.Node#attr": 0.2383656473113981,
    "org.jsoup.nodes.Node#attributes": 0.03952847075210474,
    "org.jsoup.nodes.Node#baseUri": 0.0291111254869791,
    "org.jsoup.nodes.Node#before": 0.0,
    "org.jsoup.nodes.Node#childNode": 0.16536710167730492,
    "org.jsoup.nodes.Node#childNodeSize": 0.17610411189931965,
    "org.jsoup.nodes.Node#childNodes": 0.031008683647302117,
    "org.jsoup.nodes.Node#childNodesAsArray": 0.0,
    "org.jsoup.nodes.Node#childNodesCopy": 0.0,
    "org.jsoup.nodes.Node#clone": 0.0,
    "org.jsoup.nodes.Node#doClone": 0.0,
    "org.jsoup.nodes.Node#equals": 0,
    "org.jsoup.nodes.Node#getDeepChild": 0.0,
    "org.jsoup.nodes.Node#getOutputSettings": 0.130892578601184,
    "org.jsoup.nodes.Node#hasAttr": 0.14433756729740643,
    "org.jsoup.nodes.Node#hashCode": 0.0,
    "org.jsoup.nodes.Node#indent": 0.11470786693528087,
    "org.jsoup.nodes.Node#nextSibling": 0.17666406279377406,
    "org.jsoup.nodes.Node#outerHtml": 0.130892578601184,
    "org.jsoup.nodes.Node#ownerDocument": 0.12866255886641634,
    "org.jsoup.nodes.Node#parent": 0.17690759253434063,
    "org.jsoup.nodes.Node#previousSibling": 0,
    "org.jsoup.nodes.Node#reindexChildren": 0.02795084971874737,
    "org.jsoup.nodes.Node#remove": 0.0,
    "org.jsoup.nodes.Node#removeAttr": 0.0,
    "org.jsoup.nodes.Node#removeChild": 0.02988071523335984,
    "org.jsoup.nodes.Node#reparentChild": 0.23676127348263276,
    "org.jsoup.nodes.Node#replaceChild": 0.0,
    "org.jsoup.nodes.Node#replaceWith": 0.0,
    "org.jsoup.nodes.Node#setBaseUri": 0.0,
    "org.jsoup.nodes.Node#setParentNode": 0.23676127348263276,
    "org.jsoup.nodes.Node#setSiblingIndex": 0.23676127348263276,
    "org.jsoup.nodes.Node#siblingIndex": 0.17610411189931965,
    "org.jsoup.nodes.Node#siblingNodes": 0.0,
    "org.jsoup.nodes.Node#toString": 0,
    "org.jsoup.nodes.Node#traverse": 0.0,
    "org.jsoup.nodes.Node#unwrap": 0.0,
    "org.jsoup.nodes.Node#wrap": 0.0,
    "org.jsoup.nodes.Node.1#head": 0.0,
    "org.jsoup.nodes.Node.1#tail": 0.0,
    "org.jsoup.nodes.Node.OuterHtmlVisitor#Node$OuterHtmlVisitor": 0.130892578601184,
    "org.jsoup.nodes.Node.OuterHtmlVisitor#head": 0.130892578601184,
    "org.jsoup.nodes.Node.OuterHtmlVisitor#tail": 0.130892578601184,
    "org.jsoup.nodes.TextNode#TextNode": 0.2440467650459882,
    "org.jsoup.nodes.TextNode#absUrl": 0,
    "org.jsoup.nodes.TextNode#attr": 0.0,
    "org.jsoup.nodes.TextNode#attributes": 0,
    "org.jsoup.nodes.TextNode#createFromEncoded": 0,
    "org.jsoup.nodes.TextNode#ensureAttributes": 0.0,
    "org.jsoup.nodes.TextNode#getWholeText": 0.19687932316499937,
    "org.jsoup.nodes.TextNode#hasAttr": 0,
    "org.jsoup.nodes.TextNode#isBlank": 0.06454972243679027,
    "org.jsoup.nodes.TextNode#lastCharIsWhitespace": 0.1472642081021448,
    "org.jsoup.nodes.TextNode#nodeName": 0.17385016708940756,
    "org.jsoup.nodes.TextNode#normaliseWhitespace": 0.17659435724368228,
    "org.jsoup.nodes.TextNode#outerHtmlHead": 0.1378123654176776,
    "org.jsoup.nodes.TextNode#outerHtmlTail": 0,
    "org.jsoup.nodes.TextNode#removeAttr": 0,
    "org.jsoup.nodes.TextNode#splitText": 0.0,
    "org.jsoup.nodes.TextNode#stripLeadingWhitespace": 0.05423261445466404,
    "org.jsoup.nodes.TextNode#text": 0.0,
    "org.jsoup.nodes.TextNode#toString": 0,
    "org.jsoup.nodes.XmlDeclaration#XmlDeclaration": 0.0,
    "org.jsoup.nodes.XmlDeclaration#getWholeDeclaration": 0.0,
    "org.jsoup.nodes.XmlDeclaration#nodeName": 0.0,
    "org.jsoup.nodes.XmlDeclaration#outerHtmlHead": 0.0,
    "org.jsoup.nodes.XmlDeclaration#outerHtmlTail": 0.0,
    "org.jsoup.nodes.XmlDeclaration#toString": 0,
    "org.jsoup.parser.CharacterReader#CharacterReader": 0.24112141108520607,
    "org.jsoup.parser.CharacterReader#advance": 0.23787196577216382,
    "org.jsoup.parser.CharacterReader#consume": 0.2450715406979359,
    "org.jsoup.parser.CharacterReader#consumeAsString": 0,
    "org.jsoup.parser.CharacterReader#consumeDigitSequence": 0.3380617018914066,
    "org.jsoup.parser.CharacterReader#consumeHexSequence": 0.12909944487358055,
    "org.jsoup.parser.CharacterReader#consumeLetterSequence": 0.35138211074996695,
    "org.jsoup.parser.CharacterReader#consumeLetterThenDigitSequence": 0.2906591794880899,
    "org.jsoup.parser.CharacterReader#consumeTo": 0.7236067977499789,
    "org.jsoup.parser.CharacterReader#consumeToAny": 0.23676127348263276,
    "org.jsoup.parser.CharacterReader#consumeToEnd": 0.06454972243679027,
    "org.jsoup.parser.CharacterReader#containsIgnoreCase": 0.4,
    "org.jsoup.parser.CharacterReader#current": 0.2360293976249778,
    "org.jsoup.parser.CharacterReader#isEmpty": 0.2421797398482414,
    "org.jsoup.parser.CharacterReader#mark": 0.2857738033247041,
    "org.jsoup.parser.CharacterReader#matchConsume": 0.3401680257083045,
    "org.jsoup.parser.CharacterReader#matchConsumeIgnoreCase": 0.3952847075210474,
    "org.jsoup.parser.CharacterReader#matches": 0.18257418583505539,
    "org.jsoup.parser.CharacterReader#matchesAny": 0.2811267651158746,
    "org.jsoup.parser.CharacterReader#matchesDigit": 0.22360679774997896,
    "org.jsoup.parser.CharacterReader#matchesIgnoreCase": 0.3689323936863109,
    "org.jsoup.parser.CharacterReader#matchesLetter": 0.2393774995725106,
    "org.jsoup.parser.CharacterReader#nextIndexOf": 1.3651483716701107,
    "org.jsoup.parser.CharacterReader#pos": 0.2581988897471611,
    "org.jsoup.parser.CharacterReader#rewindToMark": 0.35909242322980395,
    "org.jsoup.parser.CharacterReader#toString": 0,
    "org.jsoup.parser.CharacterReader#unconsume": 0.2897202509908427,
    "org.jsoup.parser.HtmlTreeBuilder#<clinit>": 0.21021323090253663,
    "org.jsoup.parser.HtmlTreeBuilder#HtmlTreeBuilder": 0.21021323090253663,
    "org.jsoup.parser.HtmlTreeBuilder#aboveOnStack": 0,
    "org.jsoup.parser.HtmlTreeBuilder#clearFormattingElementsToLastMarker": 0.19518001458970666,
    "org.jsoup.parser.HtmlTreeBuilder#clearStackToContext": 0.19518001458970666,
    "org.jsoup.parser.HtmlTreeBuilder#clearStackToTableBodyContext": 0.19518001458970666,
    "org.jsoup.parser.HtmlTreeBuilder#clearStackToTableContext": 0.19518001458970666,
    "org.jsoup.parser.HtmlTreeBuilder#clearStackToTableRowContext": 0.19518001458970666,
    "org.jsoup.parser.HtmlTreeBuilder#error": 0.1386750490563073,
    "org.jsoup.parser.HtmlTreeBuilder#framesetOk": 0,
    "org.jsoup.parser.HtmlTreeBuilder#generateImpliedEndTags": 0.142313613392964,
    "org.jsoup.parser.HtmlTreeBuilder#getActiveFormattingElement": 0.1613743060919757,
    "org.jsoup.parser.HtmlTreeBuilder#getBaseUri": 0.24806946917841693,
    "org.jsoup.parser.HtmlTreeBuilder#getDocument": 0.21128856368212914,
    "org.jsoup.parser.HtmlTreeBuilder#getFormElement": 0.2711630722733202,
    "org.jsoup.parser.HtmlTreeBuilder#getFromStack": 0.0,
    "org.jsoup.parser.HtmlTreeBuilder#getHeadElement": 0,
    "org.jsoup.parser.HtmlTreeBuilder#getPendingTableCharacters": 0.23717082451262844,
    "org.jsoup.parser.HtmlTreeBuilder#getStack": 0.15064871543094188,
    "org.jsoup.parser.HtmlTreeBuilder#inButtonScope": 0.21472437536770062,
    "org.jsoup.parser.HtmlTreeBuilder#inListItemScope": 0.23094010767585027,
    "org.jsoup.parser.HtmlTreeBuilder#inScope": 0.20189321327181206,
    "org.jsoup.parser.HtmlTreeBuilder#inSelectScope": 0,
    "org.jsoup.parser.HtmlTreeBuilder#inSpecificScope": 0,
    "org.jsoup.parser.HtmlTreeBuilder#inTableScope": 0.19518001458970666,
    "org.jsoup.parser.HtmlTreeBuilder#insert": 0.21773242158072692,
    "org.jsoup.parser.HtmlTreeBuilder#insertEmpty": 0.32101211891111664,
    "org.jsoup.parser.HtmlTreeBuilder#insertForm": 0.2711630722733202,
    "org.jsoup.parser.HtmlTreeBuilder#insertInFosterParent": 0.0,
    "org.jsoup.parser.HtmlTreeBuilder#insertMarkerToFormattingElements": 0.2383656473113981,
    "org.jsoup.parser.HtmlTreeBuilder#insertNode": 0.2145206476781542,
    "org.jsoup.parser.HtmlTreeBuilder#insertOnStackAfter": 0.0,
    "org.jsoup.parser.HtmlTreeBuilder#isElementInQueue": 0.0,
    "org.jsoup.parser.HtmlTreeBuilder#isFosterInserts": 0.2145206476781542,
    "org.jsoup.parser.HtmlTreeBuilder#isFragmentParsing": 0.22360679774997896,
    "org.jsoup.parser.HtmlTreeBuilder#isInActiveFormattingElements": 0.0,
    "org.jsoup.parser.HtmlTreeBuilder#isSameFormattingElement": 0.20225995873897262,
    "org.jsoup.parser.HtmlTreeBuilder#isSpecial": 0.17888543819998318,
    "org.jsoup.parser.HtmlTreeBuilder#markInsertionMode": 0.3227486121839514,
    "org.jsoup.parser.HtmlTreeBuilder#maybeSetBaseUri": 0.0,
    "org.jsoup.parser.HtmlTreeBuilder#newPendingTableCharacters": 0.23717082451262844,
    "org.jsoup.parser.HtmlTreeBuilder#onStack": 0.19733805434408158,
    "org.jsoup.parser.HtmlTreeBuilder#originalState": 0.3227486121839514,
    "org.jsoup.parser.HtmlTreeBuilder#parse": 0.3533105995630054,
    "org.jsoup.parser.HtmlTreeBuilder#parseFragment": 0.0,
    "org.jsoup.parser.HtmlTreeBuilder#pop": 0.2083022575693182,
    "org.jsoup.parser.HtmlTreeBuilder#popStackToBefore": 0,
    "org.jsoup.parser.HtmlTreeBuilder#popStackToClose": 0.2581988897471611,
    "org.jsoup.parser.HtmlTreeBuilder#process": 0.1976423537605237,
    "org.jsoup.parser.HtmlTreeBuilder#push": 0,
    "org.jsoup.parser.HtmlTreeBuilder#pushActiveFormattingElements": 0.19639610121239315,
    "org.jsoup.parser.HtmlTreeBuilder#reconstructFormattingElements": 0.0,
    "org.jsoup.parser.HtmlTreeBuilder#removeFromActiveFormattingElements": 0.17888543819998318,
    "org.jsoup.parser.HtmlTreeBuilder#removeFromStack": 0,
    "org.jsoup.parser.HtmlTreeBuilder#replaceActiveFormattingElement": 0,
    "org.jsoup.parser.HtmlTreeBuilder#replaceInQueue": 0,
    "org.jsoup.parser.HtmlTreeBuilder#replaceOnStack": 0,
    "org.jsoup.parser.HtmlTreeBuilder#resetInsertionMode": 0.16770509831248423,
    "org.jsoup.parser.HtmlTreeBuilder#setFormElement": 0.2711630722733202,
    "org.jsoup.parser.HtmlTreeBuilder#setFosterInserts": 0.0,
    "org.jsoup.parser.HtmlTreeBuilder#setHeadElement": 0.2100902925755561,
    "org.jsoup.parser.HtmlTreeBuilder#setPendingTableCharacters": 0,
    "org.jsoup.parser.HtmlTreeBuilder#state": 0.22360679774997896,
    "org.jsoup.parser.HtmlTreeBuilder#toString": 0,
    "org.jsoup.parser.HtmlTreeBuilder#transition": 0.2141798680385621,
    "org.jsoup.parser.HtmlTreeBuilderState#<clinit>": 0.2141798680385621,
    "org.jsoup.parser.HtmlTreeBuilderState#HtmlTreeBuilderState": 0.2141798680385621,
    "org.jsoup.parser.HtmlTreeBuilderState#handleRawtext": 0.26967994498529685,
    "org.jsoup.parser.HtmlTreeBuilderState#handleRcData": 0.3337119062359573,
    "org.jsoup.parser.HtmlTreeBuilderState#isWhitespace": 0.20901197770926566,
    "org.jsoup.parser.HtmlTreeBuilderState.1#process": 0.23904572186687872,
    "org.jsoup.parser.HtmlTreeBuilderState.10#process": 0.23717082451262844,
    "org.jsoup.parser.HtmlTreeBuilderState.11#process": 0.12909944487358055,
    "org.jsoup.parser.HtmlTreeBuilderState.12#anythingElse": 0,
    "org.jsoup.parser.HtmlTreeBuilderState.12#process": 0.0,
    "org.jsoup.parser.HtmlTreeBuilderState.13#anythingElse": 0.21213203435596426,
    "org.jsoup.parser.HtmlTreeBuilderState.13#exitTableBody": 0.05976143046671968,
    "org.jsoup.parser.HtmlTreeBuilderState.13#process": 0.19518001458970666,
    "org.jsoup.parser.HtmlTreeBuilderState.14#anythingElse": 0.23717082451262844,
    "org.jsoup.parser.HtmlTreeBuilderState.14#handleMissingTr": 0,
    "org.jsoup.parser.HtmlTreeBuilderState.14#process": 0.19518001458970666,
    "org.jsoup.parser.HtmlTreeBuilderState.15#anythingElse": 0.19518001458970666,
    "org.jsoup.parser.HtmlTreeBuilderState.15#closeCell": 0.0,
    "org.jsoup.parser.HtmlTreeBuilderState.15#process": 0.19518001458970666,
    "org.jsoup.parser.HtmlTreeBuilderState.16#anythingElse": 0.0,
    "org.jsoup.parser.HtmlTreeBuilderState.16#process": 0.22360679774997896,
    "org.jsoup.parser.HtmlTreeBuilderState.17#process": 0,
    "org.jsoup.parser.HtmlTreeBuilderState.18#process": 0.2176428750330035,
    "org.jsoup.parser.HtmlTreeBuilderState.19#process": 0.0,
    "org.jsoup.parser.HtmlTreeBuilderState.2#anythingElse": 0.14058038927888333,
    "org.jsoup.parser.HtmlTreeBuilderState.2#process": 0.22056438662814232,
    "org.jsoup.parser.HtmlTreeBuilderState.20#process": 0.0,
    "org.jsoup.parser.HtmlTreeBuilderState.21#process": 0.24494897427831783,
    "org.jsoup.parser.HtmlTreeBuilderState.22#process": 0.0,
    "org.jsoup.parser.HtmlTreeBuilderState.23#process": 0,
    "org.jsoup.parser.HtmlTreeBuilderState.24#<clinit>": 0.2141798680385621,
    "org.jsoup.parser.HtmlTreeBuilderState.3#process": 0.2100902925755561,
    "org.jsoup.parser.HtmlTreeBuilderState.4#anythingElse": 0.13948208816291768,
    "org.jsoup.parser.HtmlTreeBuilderState.4#process": 0.20901197770926566,
    "org.jsoup.parser.HtmlTreeBuilderState.5#anythingElse": 0.0,
    "org.jsoup.parser.HtmlTreeBuilderState.5#process": 0.0,
    "org.jsoup.parser.HtmlTreeBuilderState.6#anythingElse": 0.12804983847550624,
    "org.jsoup.parser.HtmlTreeBuilderState.6#process": 0.2100902925755561,
    "org.jsoup.parser.HtmlTreeBuilderState.7#anyOtherEndTag": 0.1419904585617662,
    "org.jsoup.parser.HtmlTreeBuilderState.7#process": 0.21486305914536244,
    "org.jsoup.parser.HtmlTreeBuilderState.8#process": 0.337099931231621,
    "org.jsoup.parser.HtmlTreeBuilderState.9#anythingElse": 0.0,
    "org.jsoup.parser.HtmlTreeBuilderState.9#process": 0,
    "org.jsoup.parser.ParseError#ParseError": 0.31622776601683794,
    "org.jsoup.parser.ParseError#getErrorMessage": 0,
    "org.jsoup.parser.ParseError#getPosition": 0,
    "org.jsoup.parser.ParseError#toString": 0.31622776601683794,
    "org.jsoup.parser.ParseErrorList#ParseErrorList": 0.23458577920427753,
    "org.jsoup.parser.ParseErrorList#canAddError": 0.33210558207753577,
    "org.jsoup.parser.ParseErrorList#getMaxSize": 0,
    "org.jsoup.parser.ParseErrorList#noTracking": 0.21053539696267973,
    "org.jsoup.parser.ParseErrorList#tracking": 0.31622776601683794,
    "org.jsoup.parser.Parser#Parser": 0.2766992952647332,
    "org.jsoup.parser.Parser#getErrors": 0.3872983346207417,
    "org.jsoup.parser.Parser#getTreeBuilder": 0,
    "org.jsoup.parser.Parser#htmlParser": 0.2958039891549808,
    "org.jsoup.parser.Parser#isTrackErrors": 0.3689323936863109,
    "org.jsoup.parser.Parser#parse": 0.24635597524338357,
    "org.jsoup.parser.Parser#parseBodyFragment": 0.043852900965351466,
    "org.jsoup.parser.Parser#parseBodyFragmentRelaxed": 0,
    "org.jsoup.parser.Parser#parseFragment": 0.03261640365267211,
    "org.jsoup.parser.Parser#parseInput": 0.3689323936863109,
    "org.jsoup.parser.Parser#parseXmlFragment": 0.0,
    "org.jsoup.parser.Parser#setTrackErrors": 0.31622776601683794,
    "org.jsoup.parser.Parser#setTreeBuilder": 0,
    "org.jsoup.parser.Parser#unescapeEntities": 0.0,
    "org.jsoup.parser.Parser#xmlParser": 0.0,
    "org.jsoup.parser.Tag#<clinit>": 0.23143213013869557,
    "org.jsoup.parser.Tag#Tag": 0.23143213013869557,
    "org.jsoup.parser.Tag#canContainBlock": 0,
    "org.jsoup.parser.Tag#equals": 0.0,
    "org.jsoup.parser.Tag#formatAsBlock": 0.1342188730482898,
    "org.jsoup.parser.Tag#getName": 0.23676127348263276,
    "org.jsoup.parser.Tag#hashCode": 0.0,
    "org.jsoup.parser.Tag#isBlock": 0.10259783520851541,
    "org.jsoup.parser.Tag#isData": 0,
    "org.jsoup.parser.Tag#isEmpty": 0,
    "org.jsoup.parser.Tag#isFormListed": 0.2145206476781542,
    "org.jsoup.parser.Tag#isFormSubmittable": 0.0,
    "org.jsoup.parser.Tag#isInline": 0.0,
    "org.jsoup.parser.Tag#isKnownTag": 0,
    "org.jsoup.parser.Tag#isSelfClosing": 0.368160520255362,
    "org.jsoup.parser.Tag#preserveWhitespace": 0.20204270845206798,
    "org.jsoup.parser.Tag#register": 0.23143213013869557,
    "org.jsoup.parser.Tag#setSelfClosing": 0.22360679774997896,
    "org.jsoup.parser.Tag#toString": 0,
    "org.jsoup.parser.Tag#valueOf": 0.23212194427697994,
    "org.jsoup.parser.Token#Token": 0.23676127348263276,
    "org.jsoup.parser.Token#asCharacter": 0.2418341467052066,
    "org.jsoup.parser.Token#asComment": 0.18136906252750293,
    "org.jsoup.parser.Token#asDoctype": 0.31008683647302115,
    "org.jsoup.parser.Token#asEndTag": 0.2141798680385621,
    "org.jsoup.parser.Token#asStartTag": 0.23712977374217598,
    "org.jsoup.parser.Token#isCharacter": 0.21520711550527918,
    "org.jsoup.parser.Token#isComment": 0.2093695690360855,
    "org.jsoup.parser.Token#isDoctype": 0.2093695690360855,
    "org.jsoup.parser.Token#isEOF": 0.25993762245501817,
    "org.jsoup.parser.Token#isEndTag": 0.2083022575693182,
    "org.jsoup.parser.Token#isStartTag": 0.2093695690360855,
    "org.jsoup.parser.Token#tokenType": 0.31622776601683794,
    "org.jsoup.parser.Token.Character#Token$Character": 0.2418341467052066,
    "org.jsoup.parser.Token.Character#getData": 0.2418341467052066,
    "org.jsoup.parser.Token.Character#toString": 0,
    "org.jsoup.parser.Token.Comment#Token$Comment": 0.18136906252750293,
    "org.jsoup.parser.Token.Comment#getData": 0.18136906252750293,
    "org.jsoup.parser.Token.Comment#toString": 0,
    "org.jsoup.parser.Token.Doctype#Token$Doctype": 0.404145188432738,
    "org.jsoup.parser.Token.Doctype#getName": 0.31008683647302115,
    "org.jsoup.parser.Token.Doctype#getPublicIdentifier": 0.31008683647302115,
    "org.jsoup.parser.Token.Doctype#getSystemIdentifier": 0.31008683647302115,
    "org.jsoup.parser.Token.Doctype#isForceQuirks": 0.2581988897471611,
    "org.jsoup.parser.Token.EOF#Token$EOF": 0.23676127348263276,
    "org.jsoup.parser.Token.EndTag#Token$EndTag": 0.17823276155980156,
    "org.jsoup.parser.Token.EndTag#toString": 0,
    "org.jsoup.parser.Token.StartTag#Token$StartTag": 0,
    "org.jsoup.parser.Token.StartTag#toString": 0,
    "org.jsoup.parser.Token.Tag#Token$Tag": 0.23712977374217598,
    "org.jsoup.parser.Token.Tag#appendAttributeName": 0.0,
    "org.jsoup.parser.Token.Tag#appendAttributeValue": 0.29814239699997197,
    "org.jsoup.parser.Token.Tag#appendTagName": 0.3380617018914066,
    "org.jsoup.parser.Token.Tag#ensureAttributeValue": 0.24794235184023236,
    "org.jsoup.parser.Token.Tag#finaliseTag": 0.24091198643696254,
    "org.jsoup.parser.Token.Tag#getAttributes": 0.0,
    "org.jsoup.parser.Token.Tag#isSelfClosing": 0.23712977374217598,
    "org.jsoup.parser.Token.Tag#name": 0,
    "org.jsoup.parser.Token.Tag#newAttribute": 0.24659848095803594,
    "org.jsoup.parser.Token.TokenType#<clinit>": 0.23676127348263276,
    "org.jsoup.parser.Token.TokenType#Token$TokenType": 0.23676127348263276,
    "org.jsoup.parser.TokenQueue#TokenQueue": 0.1252448582170299,
    "org.jsoup.parser.TokenQueue#addFirst": 0.0,
    "org.jsoup.parser.TokenQueue#advance": 0,
    "org.jsoup.parser.TokenQueue#chompBalanced": 0.08964214570007951,
    "org.jsoup.parser.TokenQueue#chompTo": 0.0,
    "org.jsoup.parser.TokenQueue#chompToIgnoreCase": 0.0,
    "org.jsoup.parser.TokenQueue#consume": 0.051298917604257706,
    "org.jsoup.parser.TokenQueue#consumeAttributeKey": 0,
    "org.jsoup.parser.TokenQueue#consumeCssIdentifier": 0.06666666666666667,
    "org.jsoup.parser.TokenQueue#consumeElementSelector": 0.13259870882635919,
    "org.jsoup.parser.TokenQueue#consumeTagName": 0,
    "org.jsoup.parser.TokenQueue#consumeTo": 0.0,
    "org.jsoup.parser.TokenQueue#consumeToAny": 0.08770580193070293,
    "org.jsoup.parser.TokenQueue#consumeToIgnoreCase": 0.0,
    "org.jsoup.parser.TokenQueue#consumeWhitespace": 0.12712834523274563,
    "org.jsoup.parser.TokenQueue#consumeWord": 0.0,
    "org.jsoup.parser.TokenQueue#isEmpty": 0.1252448582170299,
    "org.jsoup.parser.TokenQueue#matchChomp": 0.12810252304406972,
    "org.jsoup.parser.TokenQueue#matches": 0.12649110640673517,
    "org.jsoup.parser.TokenQueue#matchesAny": 0.10327955589886445,
    "org.jsoup.parser.TokenQueue#matchesCS": 0,
    "org.jsoup.parser.TokenQueue#matchesStartTag": 0,
    "org.jsoup.parser.TokenQueue#matchesWhitespace": 0.12712834523274563,
    "org.jsoup.parser.TokenQueue#matchesWord": 0.12680852498964826,
    "org.jsoup.parser.TokenQueue#peek": 0,
    "org.jsoup.parser.TokenQueue#remainder": 0.09128709291752768,
    "org.jsoup.parser.TokenQueue#remainingLength": 0.1252448582170299,
    "org.jsoup.parser.TokenQueue#toString": 0,
    "org.jsoup.parser.TokenQueue#unescape": 0.06741998624632421,
    "org.jsoup.parser.Tokeniser#Tokeniser": 0.23458577920427753,
    "org.jsoup.parser.Tokeniser#acknowledgeSelfClosingFlag": 0.4715595625715076,
    "org.jsoup.parser.Tokeniser#advanceTransition": 0.2382456847233716,
    "org.jsoup.parser.Tokeniser#appropriateEndTagName": 0.4472135954999579,
    "org.jsoup.parser.Tokeniser#characterReferenceError": 0.23717082451262844,
    "org.jsoup.parser.Tokeniser#consumeCharacterReference": 0.19069251784911848,
    "org.jsoup.parser.Tokeniser#createCommentPending": 0.18633899812498247,
    "org.jsoup.parser.Tokeniser#createDoctypePending": 0.404145188432738,
    "org.jsoup.parser.Tokeniser#createTagPending": 0.2401410661036404,
    "org.jsoup.parser.Tokeniser#createTempBuffer": 0.27937211830783126,
    "org.jsoup.parser.Tokeniser#currentNodeInHtmlNS": 0,
    "org.jsoup.parser.Tokeniser#emit": 0.3913118960624632,
    "org.jsoup.parser.Tokeniser#emitCommentPending": 0.18633899812498247,
    "org.jsoup.parser.Tokeniser#emitDoctypePending": 0.404145188432738,
    "org.jsoup.parser.Tokeniser#emitTagPending": 0.24091198643696254,
    "org.jsoup.parser.Tokeniser#eofError": 0.22360679774997896,
    "org.jsoup.parser.Tokeniser#error": 0.6577935144802719,
    "org.jsoup.parser.Tokeniser#getState": 0,
    "org.jsoup.parser.Tokeniser#isAppropriateEndTagToken": 0.27937211830783126,
    "org.jsoup.parser.Tokeniser#read": 0.48676127348263276,
    "org.jsoup.parser.Tokeniser#transition": 0.23787196577216382,
    "org.jsoup.parser.Tokeniser#unescapeEntities": 0.0,
    "org.jsoup.parser.TokeniserState#<clinit>": 0.23458577920427753,
    "org.jsoup.parser.TokeniserState#TokeniserState": 0.23458577920427753,
    "org.jsoup.parser.TokeniserState#handleDataDoubleEscapeTag": 0.0,
    "org.jsoup.parser.TokeniserState#handleDataEndTag": 0.19518001458970666,
    "org.jsoup.parser.TokeniserState$67#read": 0.3333333333333333,
    "org.jsoup.parser.TokeniserState.1#read": 0.23676127348263276,
    "org.jsoup.parser.TokeniserState.10#read": 0.2401410661036404,
    "org.jsoup.parser.TokeniserState.11#read": 0.41522739926869984,
    "org.jsoup.parser.TokeniserState.12#read": 0.34426518632954817,
    "org.jsoup.parser.TokeniserState.13#anythingElse": 0.15811388300841897,
    "org.jsoup.parser.TokeniserState.13#read": 0.34426518632954817,
    "org.jsoup.parser.TokeniserState.14#read": 0.26967994498529685,
    "org.jsoup.parser.TokeniserState.15#read": 0.26967994498529685,
    "org.jsoup.parser.TokeniserState.16#read": 0.26967994498529685,
    "org.jsoup.parser.TokeniserState.17#read": 0.2,
    "org.jsoup.parser.TokeniserState.18#read": 0.2,
    "org.jsoup.parser.TokeniserState.19#read": 0.2,
    "org.jsoup.parser.TokeniserState.2#read": 0.34156502553198664,
    "org.jsoup.parser.TokeniserState.20#read": 0.3380617018914066,
    "org.jsoup.parser.TokeniserState.21#read": 0.27386127875258304,
    "org.jsoup.parser.TokeniserState.22#read": 0.27386127875258304,
    "org.jsoup.parser.TokeniserState.23#read": 0.27386127875258304,
    "org.jsoup.parser.TokeniserState.24#read": 0.27386127875258304,
    "org.jsoup.parser.TokeniserState.25#read": 0.0,
    "org.jsoup.parser.TokeniserState.26#read": 0.0,
    "org.jsoup.parser.TokeniserState.27#read": 0.0,
    "org.jsoup.parser.TokeniserState.28#read": 0.0,
    "org.jsoup.parser.TokeniserState.29#read": 0.0,
    "org.jsoup.parser.TokeniserState.3#read": 0.408248290463863,
    "org.jsoup.parser.TokeniserState.30#read": 0,
    "org.jsoup.parser.TokeniserState.31#read": 0,
    "org.jsoup.parser.TokeniserState.32#read": 0.0,
    "org.jsoup.parser.TokeniserState.33#read": 0.0,
    "org.jsoup.parser.TokeniserState.34#read": 0.2602400194529422,
    "org.jsoup.parser.TokeniserState.35#read": 0.24659848095803594,
    "org.jsoup.parser.TokeniserState.36#read": 0.09128709291752768,
    "org.jsoup.parser.TokeniserState.37#read": 0.24794235184023236,
    "org.jsoup.parser.TokeniserState.38#read": 0.27386127875258304,
    "org.jsoup.parser.TokeniserState.39#read": 0.227866357593825,
    "org.jsoup.parser.TokeniserState.4#read": 0,
    "org.jsoup.parser.TokeniserState.40#read": 0.12621094857350137,
    "org.jsoup.parser.TokeniserState.41#read": 0.29514979597122487,
    "org.jsoup.parser.TokeniserState.42#read": 0.4791574237499549,
    "org.jsoup.parser.TokeniserState.43#read": 0.11180339887498948,
    "org.jsoup.parser.TokeniserState.44#read": 0.26967994498529685,
    "org.jsoup.parser.TokeniserState.45#read": 0.18633899812498247,
    "org.jsoup.parser.TokeniserState.46#read": 0,
    "org.jsoup.parser.TokeniserState.47#read": 0.18633899812498247,
    "org.jsoup.parser.TokeniserState.48#read": 0.18898223650461363,
    "org.jsoup.parser.TokeniserState.49#read": 0.18898223650461363,
    "org.jsoup.parser.TokeniserState.5#read": 0.26967994498529685,
    "org.jsoup.parser.TokeniserState.50#read": 0,
    "org.jsoup.parser.TokeniserState.51#read": 0.404145188432738,
    "org.jsoup.parser.TokeniserState.52#read": 0,
    "org.jsoup.parser.TokeniserState.53#read": 0.404145188432738,
    "org.jsoup.parser.TokeniserState.54#read": 0.3651483716701107,
    "org.jsoup.parser.TokeniserState.55#read": 0.3651483716701107,
    "org.jsoup.parser.TokeniserState.56#read": 0.3651483716701107,
    "org.jsoup.parser.TokeniserState.57#read": 0.3651483716701107,
    "org.jsoup.parser.TokeniserState.58#read": 0,
    "org.jsoup.parser.TokeniserState.59#read": 0.3651483716701107,
    "org.jsoup.parser.TokeniserState.6#read": 0.2,
    "org.jsoup.parser.TokeniserState.60#read": 0.3651483716701107,
    "org.jsoup.parser.TokeniserState.61#read": 0,
    "org.jsoup.parser.TokeniserState.62#read": 0,
    "org.jsoup.parser.TokeniserState.63#read": 0.3651483716701107,
    "org.jsoup.parser.TokeniserState.64#read": 0,
    "org.jsoup.parser.TokeniserState.65#read": 0.3651483716701107,
    "org.jsoup.parser.TokeniserState.66#read": 0,
    "org.jsoup.parser.TokeniserState.67#read": 0.22360679774997896,
    "org.jsoup.parser.TokeniserState.7#read": 0,
    "org.jsoup.parser.TokeniserState.8#read": 0.23975837093440766,
    "org.jsoup.parser.TokeniserState.9#read": 0.20682278742740015,
    "org.jsoup.parser.TreeBuilder#TreeBuilder": 0.2324691725103883,
    "org.jsoup.parser.TreeBuilder#currentElement": 0.23676127348263276,
    "org.jsoup.parser.TreeBuilder#initialiseParse": 0.23676127348263276,
    "org.jsoup.parser.TreeBuilder#parse": 0.40100670643214964,
    "org.jsoup.parser.TreeBuilder#runParser": 0.4367612734826328,
    "org.jsoup.parser.XmlTreeBuilder#XmlTreeBuilder": 0.15811388300841897,
    "org.jsoup.parser.XmlTreeBuilder#initialiseParse": 0.15811388300841897,
    "org.jsoup.parser.XmlTreeBuilder#insert": 0.22360679774997896,
    "org.jsoup.parser.XmlTreeBuilder#insertNode": 0.15811388300841897,
    "org.jsoup.parser.XmlTreeBuilder#parseFragment": 0.0,
    "org.jsoup.parser.XmlTreeBuilder#popStackToClose": 0.08451542547285165,
    "org.jsoup.parser.XmlTreeBuilder#process": 0.15811388300841897,
    "org.jsoup.parser.XmlTreeBuilder.1#<clinit>": 0.15811388300841897,
    "org.jsoup.safety.Cleaner#Cleaner": 0.04767312946227962,
    "org.jsoup.safety.Cleaner#clean": 0.048795003647426664,
    "org.jsoup.safety.Cleaner#copySafeNodes": 0.04767312946227962,
    "org.jsoup.safety.Cleaner#createSafeElement": 0.051298917604257706,
    "org.jsoup.safety.Cleaner#isValid": 0.0,
    "org.jsoup.safety.Cleaner.CleaningVisitor#Cleaner$CleaningVisitor": 0.04767312946227962,
    "org.jsoup.safety.Cleaner.CleaningVisitor#head": 0.04767312946227962,
    "org.jsoup.safety.Cleaner.CleaningVisitor#tail": 0.04767312946227962,
    "org.jsoup.safety.Cleaner.ElementMeta#Cleaner$ElementMeta": 0.051298917604257706,
    "org.jsoup.safety.Whitelist#Whitelist": 0.04767312946227962,
    "org.jsoup.safety.Whitelist#addAttributes": 0.051298917604257706,
    "org.jsoup.safety.Whitelist#addEnforcedAttribute": 0.07453559924999299,
    "org.jsoup.safety.Whitelist#addProtocols": 0.05423261445466404,
    "org.jsoup.safety.Whitelist#addTags": 0.05,
    "org.jsoup.safety.Whitelist#basic": 0.07453559924999299,
    "org.jsoup.safety.Whitelist#basicWithImages": 0.1,
    "org.jsoup.safety.Whitelist#getEnforcedAttributes": 0.051298917604257706,
    "org.jsoup.safety.Whitelist#isSafeAttribute": 0.0,
    "org.jsoup.safety.Whitelist#isSafeTag": 0.04767312946227962,
    "org.jsoup.safety.Whitelist#none": 0.0,
    "org.jsoup.safety.Whitelist#preserveRelativeLinks": 0.0,
    "org.jsoup.safety.Whitelist#relaxed": 0.0,
    "org.jsoup.safety.Whitelist#simpleText": 0.0,
    "org.jsoup.safety.Whitelist#testValidProtocol": 0.07905694150420949,
    "org.jsoup.safety.Whitelist.AttributeKey#Whitelist$AttributeKey": 0.05,
    "org.jsoup.safety.Whitelist.AttributeKey#valueOf": 0.05,
    "org.jsoup.safety.Whitelist.AttributeValue#Whitelist$AttributeValue": 0.07453559924999299,
    "org.jsoup.safety.Whitelist.AttributeValue#valueOf": 0.07453559924999299,
    "org.jsoup.safety.Whitelist.Protocol#Whitelist$Protocol": 0.05423261445466404,
    "org.jsoup.safety.Whitelist.Protocol#valueOf": 0.05423261445466404,
    "org.jsoup.safety.Whitelist.TagName#Whitelist$TagName": 0.04767312946227962,
    "org.jsoup.safety.Whitelist.TagName#valueOf": 0.04767312946227962,
    "org.jsoup.safety.Whitelist.TypedValue#Whitelist$TypedValue": 0.04767312946227962,
    "org.jsoup.safety.Whitelist.TypedValue#equals": 0.048795003647426664,
    "org.jsoup.safety.Whitelist.TypedValue#hashCode": 0.04767312946227962,
    "org.jsoup.safety.Whitelist.TypedValue#toString": 0.07071067811865475,
    "org.jsoup.select.Collector#Collector": 0,
    "org.jsoup.select.Collector#collect": 0.15007505629691603,
    "org.jsoup.select.Collector.Accumulator#Collector$Accumulator": 0.15007505629691603,
    "org.jsoup.select.Collector.Accumulator#head": 0.15007505629691603,
    "org.jsoup.select.Collector.Accumulator#tail": 0.15007505629691603,
    "org.jsoup.select.CombiningEvaluator#CombiningEvaluator": 0.10468478451804275,
    "org.jsoup.select.CombiningEvaluator#replaceRightMostEvaluator": 0.0,
    "org.jsoup.select.CombiningEvaluator#rightMostEvaluator": 0.0,
    "org.jsoup.select.CombiningEvaluator.And#CombiningEvaluator$And": 0.06741998624632421,
    "org.jsoup.select.CombiningEvaluator.And#matches": 0.10690449676496974,
    "org.jsoup.select.CombiningEvaluator.And#toString": 0.0,
    "org.jsoup.select.CombiningEvaluator.Or#CombiningEvaluator$Or": 0.05773502691896257,
    "org.jsoup.select.CombiningEvaluator.Or#add": 0.05773502691896257,
    "org.jsoup.select.CombiningEvaluator.Or#matches": 0.06454972243679027,
    "org.jsoup.select.CombiningEvaluator.Or#toString": 0,
    "org.jsoup.select.Elements#Elements": 0.0,
    "org.jsoup.select.Elements#add": 0.03296902366978935,
    "org.jsoup.select.Elements#addAll": 0,
    "org.jsoup.select.Elements#addClass": 0.0,
    "org.jsoup.select.Elements#after": 0.0,
    "org.jsoup.select.Elements#append": 0.0,
    "org.jsoup.select.Elements#attr": 0.0,
    "org.jsoup.select.Elements#before": 0.0,
    "org.jsoup.select.Elements#clear": 0,
    "org.jsoup.select.Elements#clone": 0.0,
    "org.jsoup.select.Elements#contains": 0,
    "org.jsoup.select.Elements#containsAll": 0,
    "org.jsoup.select.Elements#empty": 0.0,
    "org.jsoup.select.Elements#eq": 0.0,
    "org.jsoup.select.Elements#equals": 0.0,
    "org.jsoup.select.Elements#first": 0.16537964611894462,
    "org.jsoup.select.Elements#forms": 0.0,
    "org.jsoup.select.Elements#get": 0.11293848786315641,
    "org.jsoup.select.Elements#hasAttr": 0.0,
    "org.jsoup.select.Elements#hasClass": 0.0,
    "org.jsoup.select.Elements#hasText": 0.0,
    "org.jsoup.select.Elements#hashCode": 0,
    "org.jsoup.select.Elements#html": 0.0,
    "org.jsoup.select.Elements#indexOf": 0,
    "org.jsoup.select.Elements#is": 0.0,
    "org.jsoup.select.Elements#isEmpty": 0.0,
    "org.jsoup.select.Elements#iterator": 0.02839809171235324,
    "org.jsoup.select.Elements#last": 0.0,
    "org.jsoup.select.Elements#lastIndexOf": 0,
    "org.jsoup.select.Elements#listIterator": 0,
    "org.jsoup.select.Elements#not": 0.0,
    "org.jsoup.select.Elements#outerHtml": 0.0,
    "org.jsoup.select.Elements#parents": 0.0,
    "org.jsoup.select.Elements#prepend": 0.0,
    "org.jsoup.select.Elements#remove": 0,
    "org.jsoup.select.Elements#removeAll": 0,
    "org.jsoup.select.Elements#removeAttr": 0.0,
    "org.jsoup.select.Elements#removeClass": 0.0,
    "org.jsoup.select.Elements#retainAll": 0,
    "org.jsoup.select.Elements#select": 0.0,
    "org.jsoup.select.Elements#set": 0,
    "org.jsoup.select.Elements#size": 0.08233869695926183,
    "org.jsoup.select.Elements#subList": 0,
    "org.jsoup.select.Elements#tagName": 0.0,
    "org.jsoup.select.Elements#text": 0.09128709291752768,
    "org.jsoup.select.Elements#toArray": 0,
    "org.jsoup.select.Elements#toString": 0,
    "org.jsoup.select.Elements#toggleClass": 0.0,
    "org.jsoup.select.Elements#traverse": 0.0,
    "org.jsoup.select.Elements#unwrap": 0.0,
    "org.jsoup.select.Elements#val": 0.0,
    "org.jsoup.select.Elements#wrap": 0.0,
    "org.jsoup.select.Evaluator#Evaluator": 0.1494035761667992,
    "org.jsoup.select.Evaluator.AllElements#Evaluator$AllElements": 0.062017367294604234,
    "org.jsoup.select.Evaluator.AllElements#matches": 0.062017367294604234,
    "org.jsoup.select.Evaluator.AllElements#toString": 0,
    "org.jsoup.select.Evaluator.Attribute#Evaluator$Attribute": 0.05590169943749474,
    "org.jsoup.select.Evaluator.Attribute#matches": 0.05976143046671968,
    "org.jsoup.select.Evaluator.Attribute#toString": 0,
    "org.jsoup.select.Evaluator.AttributeKeyPair#Evaluator$AttributeKeyPair": 0.10540925533894598,
    "org.jsoup.select.Evaluator.AttributeStarting#Evaluator$AttributeStarting": 0.0,
    "org.jsoup.select.Evaluator.AttributeStarting#matches": 0.0,
    "org.jsoup.select.Evaluator.AttributeStarting#toString": 0,
    "org.jsoup.select.Evaluator.AttributeWithValue#Evaluator$AttributeWithValue": 0.10846522890932808,
    "org.jsoup.select.Evaluator.AttributeWithValue#matches": 0.11180339887498948,
    "org.jsoup.select.Evaluator.AttributeWithValue#toString": 0,
    "org.jsoup.select.Evaluator.AttributeWithValueContaining#Evaluator$AttributeWithValueContaining": 0.12909944487358055,
    "org.jsoup.select.Evaluator.AttributeWithValueContaining#matches": 0.12909944487358055,
    "org.jsoup.select.Evaluator.AttributeWithValueContaining#toString": 0,
    "org.jsoup.select.Evaluator.AttributeWithValueEnding#Evaluator$AttributeWithValueEnding": 0.0,
    "org.jsoup.select.Evaluator.AttributeWithValueEnding#matches": 0.0,
    "org.jsoup.select.Evaluator.AttributeWithValueEnding#toString": 0,
    "org.jsoup.select.Evaluator.AttributeWithValueMatching#Evaluator$AttributeWithValueMatching": 0.0,
    "org.jsoup.select.Evaluator.AttributeWithValueMatching#matches": 0.0,
    "org.jsoup.select.Evaluator.AttributeWithValueMatching#toString": 0,
    "org.jsoup.select.Evaluator.AttributeWithValueNot#Evaluator$AttributeWithValueNot": 0.0,
    "org.jsoup.select.Evaluator.AttributeWithValueNot#matches": 0.0,
    "org.jsoup.select.Evaluator.AttributeWithValueNot#toString": 0,
    "org.jsoup.select.Evaluator.AttributeWithValueStarting#Evaluator$AttributeWithValueStarting": 0.0,
    "org.jsoup.select.Evaluator.AttributeWithValueStarting#matches": 0.0,
    "org.jsoup.select.Evaluator.AttributeWithValueStarting#toString": 0,
    "org.jsoup.select.Evaluator.Class#Evaluator$Class": 0.1,
    "org.jsoup.select.Evaluator.Class#matches": 0.10259783520851541,
    "org.jsoup.select.Evaluator.Class#toString": 0.0,
    "org.jsoup.select.Evaluator.ContainsOwnText#Evaluator$ContainsOwnText": 0.0,
    "org.jsoup.select.Evaluator.ContainsOwnText#matches": 0.0,
    "org.jsoup.select.Evaluator.ContainsOwnText#toString": 0,
    "org.jsoup.select.Evaluator.ContainsText#Evaluator$ContainsText": 0.08451542547285165,
    "org.jsoup.select.Evaluator.ContainsText#matches": 0.08451542547285165,
    "org.jsoup.select.Evaluator.ContainsText#toString": 0,
    "org.jsoup.select.Evaluator.CssNthEvaluator#Evaluator$CssNthEvaluator": 0,
    "org.jsoup.select.Evaluator.CssNthEvaluator#matches": 0.0,
    "org.jsoup.select.Evaluator.CssNthEvaluator#toString": 0,
    "org.jsoup.select.Evaluator.Id#Evaluator$Id": 0.06984302957695782,
    "org.jsoup.select.Evaluator.Id#matches": 0.06984302957695782,
    "org.jsoup.select.Evaluator.Id#toString": 0,
    "org.jsoup.select.Evaluator.IndexEquals#Evaluator$IndexEquals": 0.0,
    "org.jsoup.select.Evaluator.IndexEquals#matches": 0.0,
    "org.jsoup.select.Evaluator.IndexEquals#toString": 0,
    "org.jsoup.select.Evaluator.IndexEvaluator#Evaluator$IndexEvaluator": 0.0,
    "org.jsoup.select.Evaluator.IndexGreaterThan#Evaluator$IndexGreaterThan": 0.0,
    "org.jsoup.select.Evaluator.IndexGreaterThan#matches": 0.0,
    "org.jsoup.select.Evaluator.IndexGreaterThan#toString": 0,
    "org.jsoup.select.Evaluator.IndexLessThan#Evaluator$IndexLessThan": 0.0,
    "org.jsoup.select.Evaluator.IndexLessThan#matches": 0.0,
    "org.jsoup.select.Evaluator.IndexLessThan#toString": 0,
    "org.jsoup.select.Evaluator.IsEmpty#Evaluator$IsEmpty": 0.0,
    "org.jsoup.select.Evaluator.IsEmpty#matches": 0.0,
    "org.jsoup.select.Evaluator.IsEmpty#toString": 0,
    "org.jsoup.select.Evaluator.IsFirstChild#Evaluator$IsFirstChild": 0.0,
    "org.jsoup.select.Evaluator.IsFirstChild#matches": 0.0,
    "org.jsoup.select.Evaluator.IsFirstChild#toString": 0,
    "org.jsoup.select.Evaluator.IsFirstOfType#Evaluator$IsFirstOfType": 0.0,
    "org.jsoup.select.Evaluator.IsFirstOfType#toString": 0,
    "org.jsoup.select.Evaluator.IsLastChild#Evaluator$IsLastChild": 0.0,
    "org.jsoup.select.Evaluator.IsLastChild#matches": 0.0,
    "org.jsoup.select.Evaluator.IsLastChild#toString": 0,
    "org.jsoup.select.Evaluator.IsLastOfType#Evaluator$IsLastOfType": 0.0,
    "org.jsoup.select.Evaluator.IsLastOfType#toString": 0,
    "org.jsoup.select.Evaluator.IsNthChild#Evaluator$IsNthChild": 0.0,
    "org.jsoup.select.Evaluator.IsNthChild#calculatePosition": 0.0,
    "org.jsoup.select.Evaluator.IsNthChild#getPseudoClass": 0,
    "org.jsoup.select.Evaluator.IsNthLastChild#Evaluator$IsNthLastChild": 0.0,
    "org.jsoup.select.Evaluator.IsNthLastChild#calculatePosition": 0.0,
    "org.jsoup.select.Evaluator.IsNthLastChild#getPseudoClass": 0,
    "org.jsoup.select.Evaluator.IsNthLastOfType#Evaluator$IsNthLastOfType": 0.0,
    "org.jsoup.select.Evaluator.IsNthLastOfType#calculatePosition": 0.0,
    "org.jsoup.select.Evaluator.IsNthLastOfType#getPseudoClass": 0,
    "org.jsoup.select.Evaluator.IsNthOfType#Evaluator$IsNthOfType": 0.0,
    "org.jsoup.select.Evaluator.IsNthOfType#calculatePosition": 0.0,
    "org.jsoup.select.Evaluator.IsNthOfType#getPseudoClass": 0,
    "org.jsoup.select.Evaluator.IsOnlyChild#Evaluator$IsOnlyChild": 0.0,
    "org.jsoup.select.Evaluator.IsOnlyChild#matches": 0.0,
    "org.jsoup.select.Evaluator.IsOnlyChild#toString": 0,
    "org.jsoup.select.Evaluator.IsOnlyOfType#Evaluator$IsOnlyOfType": 0.0,
    "org.jsoup.select.Evaluator.IsOnlyOfType#matches": 0.0,
    "org.jsoup.select.Evaluator.IsOnlyOfType#toString": 0,
    "org.jsoup.select.Evaluator.IsRoot#Evaluator$IsRoot": 0.0,
    "org.jsoup.select.Evaluator.IsRoot#matches": 0.0,
    "org.jsoup.select.Evaluator.IsRoot#toString": 0,
    "org.jsoup.select.Evaluator.Matches#Evaluator$Matches": 0.0,
    "org.jsoup.select.Evaluator.Matches#matches": 0.0,
    "org.jsoup.select.Evaluator.Matches#toString": 0,
    "org.jsoup.select.Evaluator.MatchesOwn#Evaluator$MatchesOwn": 0.0,
    "org.jsoup.select.Evaluator.MatchesOwn#matches": 0.0,
    "org.jsoup.select.Evaluator.MatchesOwn#toString": 0,
    "org.jsoup.select.Evaluator.Tag#Evaluator$Tag": 0.12777531299998798,
    "org.jsoup.select.Evaluator.Tag#matches": 0.1284322598135871,
    "org.jsoup.select.Evaluator.Tag#toString": 0.0,
    "org.jsoup.select.NodeTraversor#NodeTraversor": 0.17610411189931965,
    "org.jsoup.select.NodeTraversor#traverse": 0.17610411189931965,
    "org.jsoup.select.QueryParser#<clinit>": 0.12712834523274563,
    "org.jsoup.select.QueryParser#QueryParser": 0.12712834523274563,
    "org.jsoup.select.QueryParser#allElements": 0.08451542547285165,
    "org.jsoup.select.QueryParser#byAttribute": 0.08770580193070293,
    "org.jsoup.select.QueryParser#byClass": 0.10259783520851541,
    "org.jsoup.select.QueryParser#byId": 0.0,
    "org.jsoup.select.QueryParser#byTag": 0.13259870882635919,
    "org.jsoup.select.QueryParser#combinator": 0.08964214570007951,
    "org.jsoup.select.QueryParser#consumeIndex": 0.0,
    "org.jsoup.select.QueryParser#consumeSubQuery": 0.08964214570007951,
    "org.jsoup.select.QueryParser#contains": 0.07453559924999299,
    "org.jsoup.select.QueryParser#cssNthChild": 0.0,
    "org.jsoup.select.QueryParser#findElements": 0.12712834523274563,
    "org.jsoup.select.QueryParser#has": 0.0,
    "org.jsoup.select.QueryParser#indexEquals": 0.0,
    "org.jsoup.select.QueryParser#indexGreaterThan": 0.0,
    "org.jsoup.select.QueryParser#indexLessThan": 0.0,
    "org.jsoup.select.QueryParser#matches": 0.0,
    "org.jsoup.select.QueryParser#not": 0.0,
    "org.jsoup.select.QueryParser#parse": 0.09682458365518543,
    "org.jsoup.select.Selector#Selector": 0.12777531299998798,
    "org.jsoup.select.Selector#filterOut": 0.0,
    "org.jsoup.select.Selector#select": 0.12777531299998798,
    "org.jsoup.select.StructuralEvaluator#StructuralEvaluator": 0.06262242910851495,
    "org.jsoup.select.StructuralEvaluator.Has#StructuralEvaluator$Has": 0.0,
    "org.jsoup.select.StructuralEvaluator.Has#matches": 0.0,
    "org.jsoup.select.StructuralEvaluator.Has#toString": 0,
    "org.jsoup.select.StructuralEvaluator.ImmediateParent#StructuralEvaluator$ImmediateParent": 0.06454972243679027,
    "org.jsoup.select.StructuralEvaluator.ImmediateParent#matches": 0.06741998624632421,
    "org.jsoup.select.StructuralEvaluator.ImmediateParent#toString": 0.0,
    "org.jsoup.select.StructuralEvaluator.ImmediatePreviousSibling#StructuralEvaluator$ImmediatePreviousSibling": 0.0,
    "org.jsoup.select.StructuralEvaluator.ImmediatePreviousSibling#matches": 0.0,
    "org.jsoup.select.StructuralEvaluator.ImmediatePreviousSibling#toString": 0.0,
    "org.jsoup.select.StructuralEvaluator.Not#StructuralEvaluator$Not": 0.0,
    "org.jsoup.select.StructuralEvaluator.Not#matches": 0.0,
    "org.jsoup.select.StructuralEvaluator.Not#toString": 0,
    "org.jsoup.select.StructuralEvaluator.Parent#StructuralEvaluator$Parent": 0.04303314829119352,
    "org.jsoup.select.StructuralEvaluator.Parent#matches": 0.05,
    "org.jsoup.select.StructuralEvaluator.Parent#toString": 0,
    "org.jsoup.select.StructuralEvaluator.PreviousSibling#StructuralEvaluator$PreviousSibling": 0.0,
    "org.jsoup.select.StructuralEvaluator.PreviousSibling#matches": 0,
    "org.jsoup.select.StructuralEvaluator.PreviousSibling#toString": 0,
    "org.jsoup.select.StructuralEvaluator.Root#StructuralEvaluator$Root": 0.0,
    "org.jsoup.select.StructuralEvaluator.Root#matches": 0.0
}