{
    "org.jsoup.Connection.Method#<clinit>": 884,
    "org.jsoup.Connection.Method#Connection$Method": 884,
    "org.jsoup.Jsoup#Jsoup": 884,
    "org.jsoup.Jsoup#clean": 884,
    "org.jsoup.Jsoup#connect": 884,
    "org.jsoup.Jsoup#isValid": 884,
    "org.jsoup.Jsoup#parse": 884,
    "org.jsoup.Jsoup#parseBodyFragment": 884,
    "org.jsoup.helper.DataUtil#<clinit>": 3,
    "org.jsoup.helper.DataUtil#DataUtil": 884,
    "org.jsoup.helper.DataUtil#getCharsetFromContentType": 884,
    "org.jsoup.helper.DataUtil#load": 884,
    "org.jsoup.helper.DataUtil#parseByteData": 1,
    "org.jsoup.helper.DataUtil#readToByteBuffer": 2,
    "org.jsoup.helper.DescendableLinkedList#DescendableLinkedList": 284,
    "org.jsoup.helper.DescendableLinkedList#descendingIterator": 317,
    "org.jsoup.helper.DescendableLinkedList#peekLast": 209,
    "org.jsoup.helper.DescendableLinkedList#pollLast": 209,
    "org.jsoup.helper.DescendableLinkedList#push": 884,
    "org.jsoup.helper.DescendableLinkedList.DescendingIterator#DescendableLinkedList$DescendingIterator": 317,
    "org.jsoup.helper.DescendableLinkedList.DescendingIterator#hasNext": 317,
    "org.jsoup.helper.DescendableLinkedList.DescendingIterator#next": 314,
    "org.jsoup.helper.DescendableLinkedList.DescendingIterator#remove": 333,
    "org.jsoup.helper.HttpConnection#HttpConnection": 884,
    "org.jsoup.helper.HttpConnection#connect": 884,
    "org.jsoup.helper.HttpConnection#cookie": 884,
    "org.jsoup.helper.HttpConnection#cookies": 884,
    "org.jsoup.helper.HttpConnection#data": 884,
    "org.jsoup.helper.HttpConnection#execute": 884,
    "org.jsoup.helper.HttpConnection#followRedirects": 884,
    "org.jsoup.helper.HttpConnection#get": 884,
    "org.jsoup.helper.HttpConnection#header": 884,
    "org.jsoup.helper.HttpConnection#ignoreContentType": 884,
    "org.jsoup.helper.HttpConnection#ignoreHttpErrors": 884,
    "org.jsoup.helper.HttpConnection#method": 884,
    "org.jsoup.helper.HttpConnection#parser": 884,
    "org.jsoup.helper.HttpConnection#post": 884,
    "org.jsoup.helper.HttpConnection#referrer": 884,
    "org.jsoup.helper.HttpConnection#request": 884,
    "org.jsoup.helper.HttpConnection#response": 884,
    "org.jsoup.helper.HttpConnection#timeout": 884,
    "org.jsoup.helper.HttpConnection#url": 884,
    "org.jsoup.helper.HttpConnection#userAgent": 884,
    "org.jsoup.helper.HttpConnection.Base#HttpConnection$Base": 884,
    "org.jsoup.helper.HttpConnection.Base#cookie": 884,
    "org.jsoup.helper.HttpConnection.Base#cookies": 884,
    "org.jsoup.helper.HttpConnection.Base#getHeaderCaseInsensitive": 884,
    "org.jsoup.helper.HttpConnection.Base#hasCookie": 884,
    "org.jsoup.helper.HttpConnection.Base#hasHeader": 884,
    "org.jsoup.helper.HttpConnection.Base#header": 884,
    "org.jsoup.helper.HttpConnection.Base#headers": 884,
    "org.jsoup.helper.HttpConnection.Base#method": 884,
    "org.jsoup.helper.HttpConnection.Base#removeCookie": 884,
    "org.jsoup.helper.HttpConnection.Base#removeHeader": 884,
    "org.jsoup.helper.HttpConnection.Base#scanHeaders": 884,
    "org.jsoup.helper.HttpConnection.Base#url": 884,
    "org.jsoup.helper.HttpConnection.KeyVal#HttpConnection$KeyVal": 884,
    "org.jsoup.helper.HttpConnection.KeyVal#create": 884,
    "org.jsoup.helper.HttpConnection.KeyVal#key": 884,
    "org.jsoup.helper.HttpConnection.KeyVal#toString": 884,
    "org.jsoup.helper.HttpConnection.KeyVal#value": 884,
    "org.jsoup.helper.HttpConnection.Request#HttpConnection$Request": 884,
    "org.jsoup.helper.HttpConnection.Request#data": 884,
    "org.jsoup.helper.HttpConnection.Request#followRedirects": 884,
    "org.jsoup.helper.HttpConnection.Request#ignoreContentType": 884,
    "org.jsoup.helper.HttpConnection.Request#ignoreHttpErrors": 884,
    "org.jsoup.helper.HttpConnection.Request#parser": 884,
    "org.jsoup.helper.HttpConnection.Request#timeout": 884,
    "org.jsoup.helper.HttpConnection.Response#HttpConnection$Response": 884,
    "org.jsoup.helper.HttpConnection.Response#body": 884,
    "org.jsoup.helper.HttpConnection.Response#bodyAsBytes": 884,
    "org.jsoup.helper.HttpConnection.Response#charset": 884,
    "org.jsoup.helper.HttpConnection.Response#contentType": 884,
    "org.jsoup.helper.HttpConnection.Response#createConnection": 884,
    "org.jsoup.helper.HttpConnection.Response#execute": 884,
    "org.jsoup.helper.HttpConnection.Response#getRequestCookieString": 884,
    "org.jsoup.helper.HttpConnection.Response#parse": 884,
    "org.jsoup.helper.HttpConnection.Response#processResponseHeaders": 884,
    "org.jsoup.helper.HttpConnection.Response#serialiseRequestUrl": 884,
    "org.jsoup.helper.HttpConnection.Response#setupFromConnection": 884,
    "org.jsoup.helper.HttpConnection.Response#statusCode": 884,
    "org.jsoup.helper.HttpConnection.Response#statusMessage": 884,
    "org.jsoup.helper.HttpConnection.Response#writePost": 884,
    "org.jsoup.helper.StringUtil#<clinit>": 281,
    "org.jsoup.helper.StringUtil#StringUtil": 884,
    "org.jsoup.helper.StringUtil#in": 224,
    "org.jsoup.helper.StringUtil#isBlank": 884,
    "org.jsoup.helper.StringUtil#isNumeric": 884,
    "org.jsoup.helper.StringUtil#isWhitespace": 222,
    "org.jsoup.helper.StringUtil#join": 884,
    "org.jsoup.helper.StringUtil#normaliseWhitespace": 329,
    "org.jsoup.helper.StringUtil#padding": 884,
    "org.jsoup.helper.Validate#Validate": 884,
    "org.jsoup.helper.Validate#fail": 884,
    "org.jsoup.helper.Validate#isFalse": 261,
    "org.jsoup.helper.Validate#isTrue": 884,
    "org.jsoup.helper.Validate#noNullElements": 884,
    "org.jsoup.helper.Validate#notEmpty": 103,
    "org.jsoup.helper.Validate#notNull": 286,
    "org.jsoup.nodes.Attribute#Attribute": 265,
    "org.jsoup.nodes.Attribute#clone": 884,
    "org.jsoup.nodes.Attribute#createFromEncoded": 884,
    "org.jsoup.nodes.Attribute#equals": 884,
    "org.jsoup.nodes.Attribute#getKey": 263,
    "org.jsoup.nodes.Attribute#getValue": 171,
    "org.jsoup.nodes.Attribute#hashCode": 884,
    "org.jsoup.nodes.Attribute#html": 884,
    "org.jsoup.nodes.Attribute#isDataAttribute": 884,
    "org.jsoup.nodes.Attribute#setKey": 884,
    "org.jsoup.nodes.Attribute#setValue": 884,
    "org.jsoup.nodes.Attribute#toString": 884,
    "org.jsoup.nodes.Attributes#Attributes": 280,
    "org.jsoup.nodes.Attributes#addAll": 884,
    "org.jsoup.nodes.Attributes#asList": 884,
    "org.jsoup.nodes.Attributes#clone": 884,
    "org.jsoup.nodes.Attributes#dataKey": 884,
    "org.jsoup.nodes.Attributes#dataset": 884,
    "org.jsoup.nodes.Attributes#equals": 884,
    "org.jsoup.nodes.Attributes#get": 171,
    "org.jsoup.nodes.Attributes#hasKey": 161,
    "org.jsoup.nodes.Attributes#hashCode": 884,
    "org.jsoup.nodes.Attributes#html": 884,
    "org.jsoup.nodes.Attributes#iterator": 884,
    "org.jsoup.nodes.Attributes#put": 263,
    "org.jsoup.nodes.Attributes#remove": 884,
    "org.jsoup.nodes.Attributes#size": 884,
    "org.jsoup.nodes.Attributes#toString": 884,
    "org.jsoup.nodes.Attributes.Dataset#Attributes$Dataset": 884,
    "org.jsoup.nodes.Attributes.Dataset#entrySet": 884,
    "org.jsoup.nodes.Attributes.Dataset#put": 884,
    "org.jsoup.nodes.Attributes.Dataset.DatasetIterator#Attributes$Dataset$DatasetIterator": 884,
    "org.jsoup.nodes.Attributes.Dataset.DatasetIterator#hasNext": 884,
    "org.jsoup.nodes.Attributes.Dataset.DatasetIterator#next": 884,
    "org.jsoup.nodes.Attributes.Dataset.DatasetIterator#remove": 884,
    "org.jsoup.nodes.Attributes.Dataset.EntrySet#Attributes$Dataset$EntrySet": 884,
    "org.jsoup.nodes.Attributes.Dataset.EntrySet#iterator": 884,
    "org.jsoup.nodes.Attributes.Dataset.EntrySet#size": 884,
    "org.jsoup.nodes.Comment#Comment": 74,
    "org.jsoup.nodes.Comment#getData": 884,
    "org.jsoup.nodes.Comment#nodeName": 884,
    "org.jsoup.nodes.Comment#outerHtmlHead": 884,
    "org.jsoup.nodes.Comment#outerHtmlTail": 884,
    "org.jsoup.nodes.Comment#toString": 884,
    "org.jsoup.nodes.DataNode#DataNode": 70,
    "org.jsoup.nodes.DataNode#createFromEncoded": 884,
    "org.jsoup.nodes.DataNode#getWholeData": 884,
    "org.jsoup.nodes.DataNode#nodeName": 884,
    "org.jsoup.nodes.DataNode#outerHtmlHead": 884,
    "org.jsoup.nodes.DataNode#outerHtmlTail": 884,
    "org.jsoup.nodes.DataNode#setWholeData": 884,
    "org.jsoup.nodes.DataNode#toString": 884,
    "org.jsoup.nodes.Document#Document": 270,
    "org.jsoup.nodes.Document#body": 884,
    "org.jsoup.nodes.Document#clone": 884,
    "org.jsoup.nodes.Document#createElement": 884,
    "org.jsoup.nodes.Document#createShell": 884,
    "org.jsoup.nodes.Document#findFirstElementByTagName": 884,
    "org.jsoup.nodes.Document#head": 320,
    "org.jsoup.nodes.Document#nodeName": 367,
    "org.jsoup.nodes.Document#normalise": 884,
    "org.jsoup.nodes.Document#normaliseStructure": 884,
    "org.jsoup.nodes.Document#normaliseTextNodes": 884,
    "org.jsoup.nodes.Document#outerHtml": 884,
    "org.jsoup.nodes.Document#outputSettings": 884,
    "org.jsoup.nodes.Document#quirksMode": 884,
    "org.jsoup.nodes.Document#text": 884,
    "org.jsoup.nodes.Document#title": 884,
    "org.jsoup.nodes.Document.OutputSettings#Document$OutputSettings": 270,
    "org.jsoup.nodes.Document.OutputSettings#charset": 6,
    "org.jsoup.nodes.Document.OutputSettings#clone": 884,
    "org.jsoup.nodes.Document.OutputSettings#encoder": 351,
    "org.jsoup.nodes.Document.OutputSettings#escapeMode": 884,
    "org.jsoup.nodes.Document.OutputSettings#indentAmount": 884,
    "org.jsoup.nodes.Document.OutputSettings#prettyPrint": 884,
    "org.jsoup.nodes.Document.QuirksMode#<clinit>": 270,
    "org.jsoup.nodes.Document.QuirksMode#Document$QuirksMode": 270,
    "org.jsoup.nodes.DocumentType#DocumentType": 32,
    "org.jsoup.nodes.DocumentType#nodeName": 884,
    "org.jsoup.nodes.DocumentType#outerHtmlHead": 884,
    "org.jsoup.nodes.DocumentType#outerHtmlTail": 884,
    "org.jsoup.nodes.Element#Element": 271,
    "org.jsoup.nodes.Element#accumulateParents": 884,
    "org.jsoup.nodes.Element#addClass": 884,
    "org.jsoup.nodes.Element#after": 884,
    "org.jsoup.nodes.Element#append": 884,
    "org.jsoup.nodes.Element#appendChild": 261,
    "org.jsoup.nodes.Element#appendElement": 884,
    "org.jsoup.nodes.Element#appendNormalisedText": 121,
    "org.jsoup.nodes.Element#appendText": 884,
    "org.jsoup.nodes.Element#appendWhitespaceIfBr": 122,
    "org.jsoup.nodes.Element#attr": 884,
    "org.jsoup.nodes.Element#before": 884,
    "org.jsoup.nodes.Element#child": 884,
    "org.jsoup.nodes.Element#children": 884,
    "org.jsoup.nodes.Element#className": 272,
    "org.jsoup.nodes.Element#classNames": 884,
    "org.jsoup.nodes.Element#clone": 884,
    "org.jsoup.nodes.Element#data": 884,
    "org.jsoup.nodes.Element#dataNodes": 884,
    "org.jsoup.nodes.Element#dataset": 884,
    "org.jsoup.nodes.Element#elementSiblingIndex": 884,
    "org.jsoup.nodes.Element#empty": 884,
    "org.jsoup.nodes.Element#equals": 884,
    "org.jsoup.nodes.Element#firstElementSibling": 884,
    "org.jsoup.nodes.Element#getAllElements": 884,
    "org.jsoup.nodes.Element#getElementById": 884,
    "org.jsoup.nodes.Element#getElementsByAttribute": 884,
    "org.jsoup.nodes.Element#getElementsByAttributeStarting": 884,
    "org.jsoup.nodes.Element#getElementsByAttributeValue": 884,
    "org.jsoup.nodes.Element#getElementsByAttributeValueContaining": 884,
    "org.jsoup.nodes.Element#getElementsByAttributeValueEnding": 884,
    "org.jsoup.nodes.Element#getElementsByAttributeValueMatching": 884,
    "org.jsoup.nodes.Element#getElementsByAttributeValueNot": 884,
    "org.jsoup.nodes.Element#getElementsByAttributeValueStarting": 884,
    "org.jsoup.nodes.Element#getElementsByClass": 884,
    "org.jsoup.nodes.Element#getElementsByIndexEquals": 884,
    "org.jsoup.nodes.Element#getElementsByIndexGreaterThan": 884,
    "org.jsoup.nodes.Element#getElementsByIndexLessThan": 884,
    "org.jsoup.nodes.Element#getElementsByTag": 184,
    "org.jsoup.nodes.Element#getElementsContainingOwnText": 884,
    "org.jsoup.nodes.Element#getElementsContainingText": 884,
    "org.jsoup.nodes.Element#getElementsMatchingOwnText": 884,
    "org.jsoup.nodes.Element#getElementsMatchingText": 884,
    "org.jsoup.nodes.Element#hasClass": 169,
    "org.jsoup.nodes.Element#hasText": 884,
    "org.jsoup.nodes.Element#hashCode": 884,
    "org.jsoup.nodes.Element#html": 884,
    "org.jsoup.nodes.Element#id": 362,
    "org.jsoup.nodes.Element#indexInList": 884,
    "org.jsoup.nodes.Element#isBlock": 157,
    "org.jsoup.nodes.Element#lastElementSibling": 884,
    "org.jsoup.nodes.Element#nextElementSibling": 884,
    "org.jsoup.nodes.Element#nodeName": 261,
    "org.jsoup.nodes.Element#outerHtmlHead": 353,
    "org.jsoup.nodes.Element#outerHtmlTail": 353,
    "org.jsoup.nodes.Element#ownText": 884,
    "org.jsoup.nodes.Element#parent": 299,
    "org.jsoup.nodes.Element#parents": 884,
    "org.jsoup.nodes.Element#prepend": 884,
    "org.jsoup.nodes.Element#prependChild": 884,
    "org.jsoup.nodes.Element#prependElement": 884,
    "org.jsoup.nodes.Element#prependText": 884,
    "org.jsoup.nodes.Element#preserveWhitespace": 156,
    "org.jsoup.nodes.Element#previousElementSibling": 884,
    "org.jsoup.nodes.Element#removeClass": 884,
    "org.jsoup.nodes.Element#select": 202,
    "org.jsoup.nodes.Element#siblingElements": 884,
    "org.jsoup.nodes.Element#tag": 347,
    "org.jsoup.nodes.Element#tagName": 884,
    "org.jsoup.nodes.Element#text": 884,
    "org.jsoup.nodes.Element#textNodes": 884,
    "org.jsoup.nodes.Element#toString": 884,
    "org.jsoup.nodes.Element#toggleClass": 884,
    "org.jsoup.nodes.Element#val": 884,
    "org.jsoup.nodes.Element#wrap": 884,
    "org.jsoup.nodes.Entities#<clinit>": 280,
    "org.jsoup.nodes.Entities#Entities": 884,
    "org.jsoup.nodes.Entities#escape": 355,
    "org.jsoup.nodes.Entities#getCharacterByName": 64,
    "org.jsoup.nodes.Entities#isNamedEntity": 81,
    "org.jsoup.nodes.Entities#loadEntities": 280,
    "org.jsoup.nodes.Entities#toCharacterKey": 280,
    "org.jsoup.nodes.Entities#unescape": 884,
    "org.jsoup.nodes.Entities.EscapeMode#<clinit>": 274,
    "org.jsoup.nodes.Entities.EscapeMode#Entities$EscapeMode": 274,
    "org.jsoup.nodes.Entities.EscapeMode#getMap": 355,
    "org.jsoup.nodes.Node#Node": 183,
    "org.jsoup.nodes.Node#absUrl": 884,
    "org.jsoup.nodes.Node#addChildren": 884,
    "org.jsoup.nodes.Node#addSiblingHtml": 884,
    "org.jsoup.nodes.Node#after": 884,
    "org.jsoup.nodes.Node#attr": 54,
    "org.jsoup.nodes.Node#attributes": 884,
    "org.jsoup.nodes.Node#baseUri": 884,
    "org.jsoup.nodes.Node#before": 884,
    "org.jsoup.nodes.Node#childNode": 318,
    "org.jsoup.nodes.Node#childNodes": 325,
    "org.jsoup.nodes.Node#childNodesAsArray": 884,
    "org.jsoup.nodes.Node#clone": 884,
    "org.jsoup.nodes.Node#doClone": 884,
    "org.jsoup.nodes.Node#equals": 884,
    "org.jsoup.nodes.Node#getDeepChild": 884,
    "org.jsoup.nodes.Node#getOutputSettings": 360,
    "org.jsoup.nodes.Node#hasAttr": 149,
    "org.jsoup.nodes.Node#hashCode": 884,
    "org.jsoup.nodes.Node#indent": 884,
    "org.jsoup.nodes.Node#nextSibling": 321,
    "org.jsoup.nodes.Node#outerHtml": 360,
    "org.jsoup.nodes.Node#ownerDocument": 361,
    "org.jsoup.nodes.Node#parent": 310,
    "org.jsoup.nodes.Node#previousSibling": 884,
    "org.jsoup.nodes.Node#reindexChildren": 884,
    "org.jsoup.nodes.Node#remove": 884,
    "org.jsoup.nodes.Node#removeAttr": 884,
    "org.jsoup.nodes.Node#removeChild": 884,
    "org.jsoup.nodes.Node#reparentChild": 261,
    "org.jsoup.nodes.Node#replaceChild": 884,
    "org.jsoup.nodes.Node#replaceWith": 884,
    "org.jsoup.nodes.Node#setBaseUri": 884,
    "org.jsoup.nodes.Node#setParentNode": 261,
    "org.jsoup.nodes.Node#setSiblingIndex": 261,
    "org.jsoup.nodes.Node#siblingIndex": 325,
    "org.jsoup.nodes.Node#siblingNodes": 884,
    "org.jsoup.nodes.Node#toString": 884,
    "org.jsoup.nodes.Node#traverse": 884,
    "org.jsoup.nodes.Node#unwrap": 884,
    "org.jsoup.nodes.Node#wrap": 884,
    "org.jsoup.nodes.Node.1#head": 884,
    "org.jsoup.nodes.Node.1#tail": 884,
    "org.jsoup.nodes.Node.OuterHtmlVisitor#Node$OuterHtmlVisitor": 360,
    "org.jsoup.nodes.Node.OuterHtmlVisitor#head": 360,
    "org.jsoup.nodes.Node.OuterHtmlVisitor#tail": 360,
    "org.jsoup.nodes.TextNode#TextNode": 183,
    "org.jsoup.nodes.TextNode#absUrl": 884,
    "org.jsoup.nodes.TextNode#attr": 884,
    "org.jsoup.nodes.TextNode#attributes": 884,
    "org.jsoup.nodes.TextNode#createFromEncoded": 884,
    "org.jsoup.nodes.TextNode#ensureAttributes": 884,
    "org.jsoup.nodes.TextNode#getWholeText": 158,
    "org.jsoup.nodes.TextNode#hasAttr": 884,
    "org.jsoup.nodes.TextNode#isBlank": 884,
    "org.jsoup.nodes.TextNode#lastCharIsWhitespace": 160,
    "org.jsoup.nodes.TextNode#nodeName": 349,
    "org.jsoup.nodes.TextNode#normaliseWhitespace": 328,
    "org.jsoup.nodes.TextNode#outerHtmlHead": 348,
    "org.jsoup.nodes.TextNode#outerHtmlTail": 884,
    "org.jsoup.nodes.TextNode#removeAttr": 884,
    "org.jsoup.nodes.TextNode#splitText": 884,
    "org.jsoup.nodes.TextNode#stripLeadingWhitespace": 327,
    "org.jsoup.nodes.TextNode#text": 884,
    "org.jsoup.nodes.TextNode#toString": 884,
    "org.jsoup.parser.CharacterReader#CharacterReader": 294,
    "org.jsoup.parser.CharacterReader#advance": 261,
    "org.jsoup.parser.CharacterReader#consume": 282,
    "org.jsoup.parser.CharacterReader#consumeAsString": 884,
    "org.jsoup.parser.CharacterReader#consumeDigitSequence": 9,
    "org.jsoup.parser.CharacterReader#consumeHexSequence": 125,
    "org.jsoup.parser.CharacterReader#consumeLetterSequence": 99,
    "org.jsoup.parser.CharacterReader#consumeLetterThenDigitSequence": 59,
    "org.jsoup.parser.CharacterReader#consumeTo": 884,
    "org.jsoup.parser.CharacterReader#consumeToAny": 261,
    "org.jsoup.parser.CharacterReader#consumeToEnd": 884,
    "org.jsoup.parser.CharacterReader#containsIgnoreCase": 884,
    "org.jsoup.parser.CharacterReader#current": 266,
    "org.jsoup.parser.CharacterReader#isEmpty": 286,
    "org.jsoup.parser.CharacterReader#mark": 59,
    "org.jsoup.parser.CharacterReader#matchConsume": 56,
    "org.jsoup.parser.CharacterReader#matchConsumeIgnoreCase": 10,
    "org.jsoup.parser.CharacterReader#matches": 105,
    "org.jsoup.parser.CharacterReader#matchesAny": 60,
    "org.jsoup.parser.CharacterReader#matchesDigit": 82,
    "org.jsoup.parser.CharacterReader#matchesIgnoreCase": 33,
    "org.jsoup.parser.CharacterReader#matchesLetter": 305,
    "org.jsoup.parser.CharacterReader#nextIndexOf": 884,
    "org.jsoup.parser.CharacterReader#pos": 884,
    "org.jsoup.parser.CharacterReader#rewindToMark": 20,
    "org.jsoup.parser.CharacterReader#toString": 884,
    "org.jsoup.parser.CharacterReader#unconsume": 186,
    "org.jsoup.parser.HtmlTreeBuilder#<clinit>": 276,
    "org.jsoup.parser.HtmlTreeBuilder#HtmlTreeBuilder": 276,
    "org.jsoup.parser.HtmlTreeBuilder#aboveOnStack": 884,
    "org.jsoup.parser.HtmlTreeBuilder#clearFormattingElementsToLastMarker": 146,
    "org.jsoup.parser.HtmlTreeBuilder#clearStackToContext": 146,
    "org.jsoup.parser.HtmlTreeBuilder#clearStackToTableBodyContext": 146,
    "org.jsoup.parser.HtmlTreeBuilder#clearStackToTableContext": 146,
    "org.jsoup.parser.HtmlTreeBuilder#clearStackToTableRowContext": 146,
    "org.jsoup.parser.HtmlTreeBuilder#error": 160,
    "org.jsoup.parser.HtmlTreeBuilder#framesetOk": 884,
    "org.jsoup.parser.HtmlTreeBuilder#generateImpliedEndTags": 306,
    "org.jsoup.parser.HtmlTreeBuilder#getActiveFormattingElement": 131,
    "org.jsoup.parser.HtmlTreeBuilder#getBaseUri": 18,
    "org.jsoup.parser.HtmlTreeBuilder#getDocument": 76,
    "org.jsoup.parser.HtmlTreeBuilder#getFormElement": 8,
    "org.jsoup.parser.HtmlTreeBuilder#getFromStack": 884,
    "org.jsoup.parser.HtmlTreeBuilder#getHeadElement": 884,
    "org.jsoup.parser.HtmlTreeBuilder#getPendingTableCharacters": 113,
    "org.jsoup.parser.HtmlTreeBuilder#getStack": 307,
    "org.jsoup.parser.HtmlTreeBuilder#inButtonScope": 330,
    "org.jsoup.parser.HtmlTreeBuilder#inListItemScope": 86,
    "org.jsoup.parser.HtmlTreeBuilder#inScope": 312,
    "org.jsoup.parser.HtmlTreeBuilder#inSelectScope": 884,
    "org.jsoup.parser.HtmlTreeBuilder#inSpecificScope": 884,
    "org.jsoup.parser.HtmlTreeBuilder#inTableScope": 146,
    "org.jsoup.parser.HtmlTreeBuilder#insert": 183,
    "org.jsoup.parser.HtmlTreeBuilder#insertEmpty": 102,
    "org.jsoup.parser.HtmlTreeBuilder#insertInFosterParent": 884,
    "org.jsoup.parser.HtmlTreeBuilder#insertMarkerToFormattingElements": 146,
    "org.jsoup.parser.HtmlTreeBuilder#insertNode": 233,
    "org.jsoup.parser.HtmlTreeBuilder#insertOnStackAfter": 884,
    "org.jsoup.parser.HtmlTreeBuilder#isElementInQueue": 884,
    "org.jsoup.parser.HtmlTreeBuilder#isFosterInserts": 233,
    "org.jsoup.parser.HtmlTreeBuilder#isFragmentParsing": 53,
    "org.jsoup.parser.HtmlTreeBuilder#isInActiveFormattingElements": 884,
    "org.jsoup.parser.HtmlTreeBuilder#isSameFormattingElement": 98,
    "org.jsoup.parser.HtmlTreeBuilder#isSpecial": 151,
    "org.jsoup.parser.HtmlTreeBuilder#markInsertionMode": 98,
    "org.jsoup.parser.HtmlTreeBuilder#maybeSetBaseUri": 884,
    "org.jsoup.parser.HtmlTreeBuilder#newPendingTableCharacters": 113,
    "org.jsoup.parser.HtmlTreeBuilder#onStack": 175,
    "org.jsoup.parser.HtmlTreeBuilder#originalState": 98,
    "org.jsoup.parser.HtmlTreeBuilder#parse": 192,
    "org.jsoup.parser.HtmlTreeBuilder#parseFragment": 884,
    "org.jsoup.parser.HtmlTreeBuilder#pop": 209,
    "org.jsoup.parser.HtmlTreeBuilder#popStackToBefore": 884,
    "org.jsoup.parser.HtmlTreeBuilder#popStackToClose": 65,
    "org.jsoup.parser.HtmlTreeBuilder#process": 89,
    "org.jsoup.parser.HtmlTreeBuilder#push": 884,
    "org.jsoup.parser.HtmlTreeBuilder#pushActiveFormattingElements": 178,
    "org.jsoup.parser.HtmlTreeBuilder#reconstructFormattingElements": 884,
    "org.jsoup.parser.HtmlTreeBuilder#removeFromActiveFormattingElements": 169,
    "org.jsoup.parser.HtmlTreeBuilder#removeFromStack": 884,
    "org.jsoup.parser.HtmlTreeBuilder#replaceActiveFormattingElement": 884,
    "org.jsoup.parser.HtmlTreeBuilder#replaceInQueue": 884,
    "org.jsoup.parser.HtmlTreeBuilder#replaceOnStack": 884,
    "org.jsoup.parser.HtmlTreeBuilder#resetInsertionMode": 311,
    "org.jsoup.parser.HtmlTreeBuilder#setFormElement": 8,
    "org.jsoup.parser.HtmlTreeBuilder#setFosterInserts": 146,
    "org.jsoup.parser.HtmlTreeBuilder#setHeadElement": 195,
    "org.jsoup.parser.HtmlTreeBuilder#setPendingTableCharacters": 884,
    "org.jsoup.parser.HtmlTreeBuilder#state": 169,
    "org.jsoup.parser.HtmlTreeBuilder#toString": 884,
    "org.jsoup.parser.HtmlTreeBuilder#transition": 233,
    "org.jsoup.parser.HtmlTreeBuilderState#<clinit>": 233,
    "org.jsoup.parser.HtmlTreeBuilderState#HtmlTreeBuilderState": 233,
    "org.jsoup.parser.HtmlTreeBuilderState#handleRawtext": 26,
    "org.jsoup.parser.HtmlTreeBuilderState#handleRcData": 35,
    "org.jsoup.parser.HtmlTreeBuilderState#isWhitespace": 204,
    "org.jsoup.parser.HtmlTreeBuilderState.1#process": 18,
    "org.jsoup.parser.HtmlTreeBuilderState.10#process": 113,
    "org.jsoup.parser.HtmlTreeBuilderState.11#process": 102,
    "org.jsoup.parser.HtmlTreeBuilderState.12#anythingElse": 884,
    "org.jsoup.parser.HtmlTreeBuilderState.12#process": 884,
    "org.jsoup.parser.HtmlTreeBuilderState.13#anythingElse": 127,
    "org.jsoup.parser.HtmlTreeBuilderState.13#exitTableBody": 341,
    "org.jsoup.parser.HtmlTreeBuilderState.13#process": 146,
    "org.jsoup.parser.HtmlTreeBuilderState.14#anythingElse": 104,
    "org.jsoup.parser.HtmlTreeBuilderState.14#handleMissingTr": 884,
    "org.jsoup.parser.HtmlTreeBuilderState.14#process": 146,
    "org.jsoup.parser.HtmlTreeBuilderState.15#anythingElse": 146,
    "org.jsoup.parser.HtmlTreeBuilderState.15#closeCell": 336,
    "org.jsoup.parser.HtmlTreeBuilderState.15#process": 146,
    "org.jsoup.parser.HtmlTreeBuilderState.16#anythingElse": 884,
    "org.jsoup.parser.HtmlTreeBuilderState.16#process": 169,
    "org.jsoup.parser.HtmlTreeBuilderState.17#process": 884,
    "org.jsoup.parser.HtmlTreeBuilderState.18#process": 36,
    "org.jsoup.parser.HtmlTreeBuilderState.19#process": 884,
    "org.jsoup.parser.HtmlTreeBuilderState.2#anythingElse": 364,
    "org.jsoup.parser.HtmlTreeBuilderState.2#process": 35,
    "org.jsoup.parser.HtmlTreeBuilderState.20#process": 884,
    "org.jsoup.parser.HtmlTreeBuilderState.21#process": 20,
    "org.jsoup.parser.HtmlTreeBuilderState.22#process": 884,
    "org.jsoup.parser.HtmlTreeBuilderState.23#process": 884,
    "org.jsoup.parser.HtmlTreeBuilderState.24#<clinit>": 233,
    "org.jsoup.parser.HtmlTreeBuilderState.3#process": 195,
    "org.jsoup.parser.HtmlTreeBuilderState.4#anythingElse": 365,
    "org.jsoup.parser.HtmlTreeBuilderState.4#process": 204,
    "org.jsoup.parser.HtmlTreeBuilderState.5#anythingElse": 884,
    "org.jsoup.parser.HtmlTreeBuilderState.5#process": 884,
    "org.jsoup.parser.HtmlTreeBuilderState.6#anythingElse": 363,
    "org.jsoup.parser.HtmlTreeBuilderState.6#process": 195,
    "org.jsoup.parser.HtmlTreeBuilderState.7#anyOtherEndTag": 132,
    "org.jsoup.parser.HtmlTreeBuilderState.7#process": 226,
    "org.jsoup.parser.HtmlTreeBuilderState.8#process": 88,
    "org.jsoup.parser.HtmlTreeBuilderState.9#anythingElse": 146,
    "org.jsoup.parser.HtmlTreeBuilderState.9#process": 146,
    "org.jsoup.parser.ParseError#ParseError": 884,
    "org.jsoup.parser.ParseError#getErrorMessage": 884,
    "org.jsoup.parser.ParseError#getPosition": 884,
    "org.jsoup.parser.ParseError#toString": 884,
    "org.jsoup.parser.ParseErrorList#ParseErrorList": 261,
    "org.jsoup.parser.ParseErrorList#canAddError": 162,
    "org.jsoup.parser.ParseErrorList#getMaxSize": 884,
    "org.jsoup.parser.ParseErrorList#noTracking": 234,
    "org.jsoup.parser.ParseErrorList#tracking": 884,
    "org.jsoup.parser.Parser#Parser": 21,
    "org.jsoup.parser.Parser#getErrors": 884,
    "org.jsoup.parser.Parser#getTreeBuilder": 884,
    "org.jsoup.parser.Parser#htmlParser": 12,
    "org.jsoup.parser.Parser#isTrackErrors": 5,
    "org.jsoup.parser.Parser#parse": 884,
    "org.jsoup.parser.Parser#parseBodyFragment": 884,
    "org.jsoup.parser.Parser#parseBodyFragmentRelaxed": 884,
    "org.jsoup.parser.Parser#parseFragment": 884,
    "org.jsoup.parser.Parser#parseInput": 5,
    "org.jsoup.parser.Parser#setTrackErrors": 884,
    "org.jsoup.parser.Parser#setTreeBuilder": 884,
    "org.jsoup.parser.Parser#xmlParser": 884,
    "org.jsoup.parser.Tag#<clinit>": 289,
    "org.jsoup.parser.Tag#Tag": 289,
    "org.jsoup.parser.Tag#canContainBlock": 884,
    "org.jsoup.parser.Tag#equals": 884,
    "org.jsoup.parser.Tag#formatAsBlock": 350,
    "org.jsoup.parser.Tag#getName": 261,
    "org.jsoup.parser.Tag#hashCode": 884,
    "org.jsoup.parser.Tag#isBlock": 174,
    "org.jsoup.parser.Tag#isData": 884,
    "org.jsoup.parser.Tag#isEmpty": 884,
    "org.jsoup.parser.Tag#isInline": 884,
    "org.jsoup.parser.Tag#isKnownTag": 313,
    "org.jsoup.parser.Tag#isSelfClosing": 884,
    "org.jsoup.parser.Tag#preserveWhitespace": 156,
    "org.jsoup.parser.Tag#register": 289,
    "org.jsoup.parser.Tag#setSelfClosing": 884,
    "org.jsoup.parser.Tag#toString": 884,
    "org.jsoup.parser.Tag#valueOf": 884,
    "org.jsoup.parser.Token#Token": 261,
    "org.jsoup.parser.Token#asCharacter": 189,
    "org.jsoup.parser.Token#asComment": 74,
    "org.jsoup.parser.Token#asDoctype": 18,
    "org.jsoup.parser.Token#asEndTag": 227,
    "org.jsoup.parser.Token#asStartTag": 261,
    "org.jsoup.parser.Token#isCharacter": 225,
    "org.jsoup.parser.Token#isComment": 198,
    "org.jsoup.parser.Token#isDoctype": 198,
    "org.jsoup.parser.Token#isEOF": 87,
    "org.jsoup.parser.Token#isEndTag": 209,
    "org.jsoup.parser.Token#isStartTag": 198,
    "org.jsoup.parser.Token#tokenType": 884,
    "org.jsoup.parser.Token.Character#Token$Character": 189,
    "org.jsoup.parser.Token.Character#getData": 189,
    "org.jsoup.parser.Token.Character#toString": 884,
    "org.jsoup.parser.Token.Comment#Token$Comment": 74,
    "org.jsoup.parser.Token.Comment#getData": 74,
    "org.jsoup.parser.Token.Comment#toString": 884,
    "org.jsoup.parser.Token.Doctype#Token$Doctype": 32,
    "org.jsoup.parser.Token.Doctype#getName": 18,
    "org.jsoup.parser.Token.Doctype#getPublicIdentifier": 18,
    "org.jsoup.parser.Token.Doctype#getSystemIdentifier": 18,
    "org.jsoup.parser.Token.Doctype#isForceQuirks": 11,
    "org.jsoup.parser.Token.EOF#Token$EOF": 261,
    "org.jsoup.parser.Token.EndTag#Token$EndTag": 334,
    "org.jsoup.parser.Token.EndTag#toString": 884,
    "org.jsoup.parser.Token.StartTag#Token$StartTag": 884,
    "org.jsoup.parser.Token.StartTag#toString": 884,
    "org.jsoup.parser.Token.Tag#Token$Tag": 261,
    "org.jsoup.parser.Token.Tag#appendAttributeName": 884,
    "org.jsoup.parser.Token.Tag#appendAttributeValue": 49,
    "org.jsoup.parser.Token.Tag#appendTagName": 51,
    "org.jsoup.parser.Token.Tag#finaliseTag": 301,
    "org.jsoup.parser.Token.Tag#getAttributes": 884,
    "org.jsoup.parser.Token.Tag#isSelfClosing": 261,
    "org.jsoup.parser.Token.Tag#name": 884,
    "org.jsoup.parser.Token.Tag#newAttribute": 180,
    "org.jsoup.parser.Token.TokenType#<clinit>": 261,
    "org.jsoup.parser.Token.TokenType#Token$TokenType": 261,
    "org.jsoup.parser.TokenQueue#TokenQueue": 221,
    "org.jsoup.parser.TokenQueue#addFirst": 884,
    "org.jsoup.parser.TokenQueue#advance": 884,
    "org.jsoup.parser.TokenQueue#chompBalanced": 131,
    "org.jsoup.parser.TokenQueue#chompTo": 884,
    "org.jsoup.parser.TokenQueue#chompToIgnoreCase": 884,
    "org.jsoup.parser.TokenQueue#consume": 320,
    "org.jsoup.parser.TokenQueue#consumeAttributeKey": 884,
    "org.jsoup.parser.TokenQueue#consumeCssIdentifier": 163,
    "org.jsoup.parser.TokenQueue#consumeElementSelector": 191,
    "org.jsoup.parser.TokenQueue#consumeTagName": 884,
    "org.jsoup.parser.TokenQueue#consumeTo": 884,
    "org.jsoup.parser.TokenQueue#consumeToAny": 117,
    "org.jsoup.parser.TokenQueue#consumeToIgnoreCase": 884,
    "org.jsoup.parser.TokenQueue#consumeWhitespace": 215,
    "org.jsoup.parser.TokenQueue#consumeWord": 884,
    "org.jsoup.parser.TokenQueue#isEmpty": 221,
    "org.jsoup.parser.TokenQueue#matchChomp": 202,
    "org.jsoup.parser.TokenQueue#matches": 217,
    "org.jsoup.parser.TokenQueue#matchesAny": 120,
    "org.jsoup.parser.TokenQueue#matchesCS": 884,
    "org.jsoup.parser.TokenQueue#matchesStartTag": 884,
    "org.jsoup.parser.TokenQueue#matchesWhitespace": 215,
    "org.jsoup.parser.TokenQueue#matchesWord": 216,
    "org.jsoup.parser.TokenQueue#peek": 884,
    "org.jsoup.parser.TokenQueue#remainder": 117,
    "org.jsoup.parser.TokenQueue#remainingLength": 221,
    "org.jsoup.parser.TokenQueue#toString": 884,
    "org.jsoup.parser.TokenQueue#unescape": 215,
    "org.jsoup.parser.Tokeniser#Tokeniser": 261,
    "org.jsoup.parser.Tokeniser#acknowledgeSelfClosingFlag": 106,
    "org.jsoup.parser.Tokeniser#advanceTransition": 236,
    "org.jsoup.parser.Tokeniser#appropriateEndTagName": 884,
    "org.jsoup.parser.Tokeniser#characterReferenceError": 884,
    "org.jsoup.parser.Tokeniser#consumeCharacterReference": 64,
    "org.jsoup.parser.Tokeniser#createCommentPending": 70,
    "org.jsoup.parser.Tokeniser#createDoctypePending": 32,
    "org.jsoup.parser.Tokeniser#createTagPending": 303,
    "org.jsoup.parser.Tokeniser#createTempBuffer": 84,
    "org.jsoup.parser.Tokeniser#currentNodeInHtmlNS": 884,
    "org.jsoup.parser.Tokeniser#emit": 59,
    "org.jsoup.parser.Tokeniser#emitCommentPending": 70,
    "org.jsoup.parser.Tokeniser#emitDoctypePending": 32,
    "org.jsoup.parser.Tokeniser#emitTagPending": 301,
    "org.jsoup.parser.Tokeniser#eofError": 884,
    "org.jsoup.parser.Tokeniser#error": 148,
    "org.jsoup.parser.Tokeniser#getState": 884,
    "org.jsoup.parser.Tokeniser#isAppropriateEndTagToken": 84,
    "org.jsoup.parser.Tokeniser#read": 261,
    "org.jsoup.parser.Tokeniser#transition": 236,
    "org.jsoup.parser.TokeniserState#<clinit>": 261,
    "org.jsoup.parser.TokeniserState#TokeniserState": 261,
    "org.jsoup.parser.TokeniserState.1#read": 261,
    "org.jsoup.parser.TokeniserState.10#read": 303,
    "org.jsoup.parser.TokeniserState.11#read": 51,
    "org.jsoup.parser.TokeniserState.12#read": 47,
    "org.jsoup.parser.TokeniserState.13#anythingElse": 884,
    "org.jsoup.parser.TokeniserState.13#read": 47,
    "org.jsoup.parser.TokeniserState.14#read": 26,
    "org.jsoup.parser.TokeniserState.15#read": 26,
    "org.jsoup.parser.TokeniserState.16#anythingElse": 884,
    "org.jsoup.parser.TokeniserState.16#read": 26,
    "org.jsoup.parser.TokeniserState.17#read": 81,
    "org.jsoup.parser.TokeniserState.18#read": 81,
    "org.jsoup.parser.TokeniserState.19#anythingElse": 125,
    "org.jsoup.parser.TokeniserState.19#read": 81,
    "org.jsoup.parser.TokeniserState.2#read": 48,
    "org.jsoup.parser.TokeniserState.20#read": 56,
    "org.jsoup.parser.TokeniserState.21#read": 94,
    "org.jsoup.parser.TokeniserState.22#read": 94,
    "org.jsoup.parser.TokeniserState.23#read": 94,
    "org.jsoup.parser.TokeniserState.24#read": 94,
    "org.jsoup.parser.TokeniserState.25#read": 884,
    "org.jsoup.parser.TokeniserState.26#read": 884,
    "org.jsoup.parser.TokeniserState.27#anythingElse": 884,
    "org.jsoup.parser.TokeniserState.27#read": 884,
    "org.jsoup.parser.TokeniserState.28#read": 884,
    "org.jsoup.parser.TokeniserState.29#read": 884,
    "org.jsoup.parser.TokeniserState.3#read": 52,
    "org.jsoup.parser.TokeniserState.30#read": 884,
    "org.jsoup.parser.TokeniserState.31#read": 884,
    "org.jsoup.parser.TokeniserState.32#read": 884,
    "org.jsoup.parser.TokeniserState.33#read": 884,
    "org.jsoup.parser.TokeniserState.34#read": 186,
    "org.jsoup.parser.TokeniserState.35#read": 180,
    "org.jsoup.parser.TokeniserState.36#read": 150,
    "org.jsoup.parser.TokeniserState.37#read": 177,
    "org.jsoup.parser.TokeniserState.38#read": 47,
    "org.jsoup.parser.TokeniserState.39#read": 340,
    "org.jsoup.parser.TokeniserState.4#read": 884,
    "org.jsoup.parser.TokeniserState.40#read": 337,
    "org.jsoup.parser.TokeniserState.41#read": 126,
    "org.jsoup.parser.TokeniserState.42#read": 128,
    "org.jsoup.parser.TokeniserState.43#read": 169,
    "org.jsoup.parser.TokeniserState.44#read": 75,
    "org.jsoup.parser.TokeniserState.45#read": 70,
    "org.jsoup.parser.TokeniserState.46#read": 884,
    "org.jsoup.parser.TokeniserState.47#read": 70,
    "org.jsoup.parser.TokeniserState.48#read": 64,
    "org.jsoup.parser.TokeniserState.49#read": 64,
    "org.jsoup.parser.TokeniserState.5#read": 26,
    "org.jsoup.parser.TokeniserState.50#read": 884,
    "org.jsoup.parser.TokeniserState.51#read": 32,
    "org.jsoup.parser.TokeniserState.52#read": 884,
    "org.jsoup.parser.TokeniserState.53#read": 32,
    "org.jsoup.parser.TokeniserState.54#read": 47,
    "org.jsoup.parser.TokeniserState.55#read": 47,
    "org.jsoup.parser.TokeniserState.56#read": 47,
    "org.jsoup.parser.TokeniserState.57#read": 47,
    "org.jsoup.parser.TokeniserState.58#read": 884,
    "org.jsoup.parser.TokeniserState.59#read": 47,
    "org.jsoup.parser.TokeniserState.6#read": 81,
    "org.jsoup.parser.TokeniserState.60#read": 47,
    "org.jsoup.parser.TokeniserState.61#read": 884,
    "org.jsoup.parser.TokeniserState.62#read": 884,
    "org.jsoup.parser.TokeniserState.63#read": 47,
    "org.jsoup.parser.TokeniserState.64#read": 884,
    "org.jsoup.parser.TokeniserState.65#read": 47,
    "org.jsoup.parser.TokeniserState.66#read": 884,
    "org.jsoup.parser.TokeniserState.67#read": 884,
    "org.jsoup.parser.TokeniserState.7#read": 884,
    "org.jsoup.parser.TokeniserState.8#read": 305,
    "org.jsoup.parser.TokeniserState.9#read": 309,
    "org.jsoup.parser.TreeBuilder#TreeBuilder": 284,
    "org.jsoup.parser.TreeBuilder#currentElement": 261,
    "org.jsoup.parser.TreeBuilder#initialiseParse": 261,
    "org.jsoup.parser.TreeBuilder#parse": 205,
    "org.jsoup.parser.TreeBuilder#runParser": 261,
    "org.jsoup.parser.XmlTreeBuilder#XmlTreeBuilder": 884,
    "org.jsoup.parser.XmlTreeBuilder#initialiseParse": 884,
    "org.jsoup.parser.XmlTreeBuilder#insert": 884,
    "org.jsoup.parser.XmlTreeBuilder#insertNode": 884,
    "org.jsoup.parser.XmlTreeBuilder#popStackToClose": 884,
    "org.jsoup.parser.XmlTreeBuilder#process": 884,
    "org.jsoup.parser.XmlTreeBuilder.1#<clinit>": 884,
    "org.jsoup.safety.Cleaner#Cleaner": 884,
    "org.jsoup.safety.Cleaner#clean": 884,
    "org.jsoup.safety.Cleaner#copySafeNodes": 884,
    "org.jsoup.safety.Cleaner#createSafeElement": 884,
    "org.jsoup.safety.Cleaner#isValid": 884,
    "org.jsoup.safety.Cleaner.ElementMeta#Cleaner$ElementMeta": 884,
    "org.jsoup.safety.Whitelist#Whitelist": 884,
    "org.jsoup.safety.Whitelist#addAttributes": 884,
    "org.jsoup.safety.Whitelist#addEnforcedAttribute": 884,
    "org.jsoup.safety.Whitelist#addProtocols": 884,
    "org.jsoup.safety.Whitelist#addTags": 884,
    "org.jsoup.safety.Whitelist#basic": 884,
    "org.jsoup.safety.Whitelist#basicWithImages": 884,
    "org.jsoup.safety.Whitelist#getEnforcedAttributes": 884,
    "org.jsoup.safety.Whitelist#isSafeAttribute": 884,
    "org.jsoup.safety.Whitelist#isSafeTag": 884,
    "org.jsoup.safety.Whitelist#none": 884,
    "org.jsoup.safety.Whitelist#preserveRelativeLinks": 884,
    "org.jsoup.safety.Whitelist#relaxed": 884,
    "org.jsoup.safety.Whitelist#simpleText": 884,
    "org.jsoup.safety.Whitelist#testValidProtocol": 884,
    "org.jsoup.safety.Whitelist.AttributeKey#Whitelist$AttributeKey": 884,
    "org.jsoup.safety.Whitelist.AttributeKey#valueOf": 884,
    "org.jsoup.safety.Whitelist.AttributeValue#Whitelist$AttributeValue": 884,
    "org.jsoup.safety.Whitelist.AttributeValue#valueOf": 884,
    "org.jsoup.safety.Whitelist.Protocol#Whitelist$Protocol": 884,
    "org.jsoup.safety.Whitelist.Protocol#valueOf": 884,
    "org.jsoup.safety.Whitelist.TagName#Whitelist$TagName": 884,
    "org.jsoup.safety.Whitelist.TagName#valueOf": 884,
    "org.jsoup.safety.Whitelist.TypedValue#Whitelist$TypedValue": 884,
    "org.jsoup.safety.Whitelist.TypedValue#equals": 884,
    "org.jsoup.safety.Whitelist.TypedValue#hashCode": 884,
    "org.jsoup.safety.Whitelist.TypedValue#toString": 884,
    "org.jsoup.select.Collector#Collector": 884,
    "org.jsoup.select.Collector#collect": 293,
    "org.jsoup.select.Collector.Accumulator#Collector$Accumulator": 293,
    "org.jsoup.select.Collector.Accumulator#head": 293,
    "org.jsoup.select.Collector.Accumulator#tail": 293,
    "org.jsoup.select.CombiningEvaluator#CombiningEvaluator": 114,
    "org.jsoup.select.CombiningEvaluator#replaceRightMostEvaluator": 884,
    "org.jsoup.select.CombiningEvaluator#rightMostEvaluator": 884,
    "org.jsoup.select.CombiningEvaluator.And#CombiningEvaluator$And": 308,
    "org.jsoup.select.CombiningEvaluator.And#matches": 107,
    "org.jsoup.select.CombiningEvaluator.And#toString": 884,
    "org.jsoup.select.CombiningEvaluator.Or#CombiningEvaluator$Or": 120,
    "org.jsoup.select.CombiningEvaluator.Or#add": 120,
    "org.jsoup.select.CombiningEvaluator.Or#matches": 102,
    "org.jsoup.select.CombiningEvaluator.Or#toString": 884,
    "org.jsoup.select.Elements#Elements": 884,
    "org.jsoup.select.Elements#add": 884,
    "org.jsoup.select.Elements#addAll": 884,
    "org.jsoup.select.Elements#addClass": 884,
    "org.jsoup.select.Elements#after": 884,
    "org.jsoup.select.Elements#append": 884,
    "org.jsoup.select.Elements#attr": 884,
    "org.jsoup.select.Elements#before": 884,
    "org.jsoup.select.Elements#clear": 884,
    "org.jsoup.select.Elements#clone": 884,
    "org.jsoup.select.Elements#contains": 884,
    "org.jsoup.select.Elements#containsAll": 884,
    "org.jsoup.select.Elements#empty": 884,
    "org.jsoup.select.Elements#eq": 884,
    "org.jsoup.select.Elements#equals": 884,
    "org.jsoup.select.Elements#first": 152,
    "org.jsoup.select.Elements#get": 366,
    "org.jsoup.select.Elements#hasAttr": 884,
    "org.jsoup.select.Elements#hasClass": 884,
    "org.jsoup.select.Elements#hasText": 884,
    "org.jsoup.select.Elements#hashCode": 884,
    "org.jsoup.select.Elements#html": 884,
    "org.jsoup.select.Elements#indexOf": 884,
    "org.jsoup.select.Elements#is": 884,
    "org.jsoup.select.Elements#isEmpty": 884,
    "org.jsoup.select.Elements#iterator": 884,
    "org.jsoup.select.Elements#last": 884,
    "org.jsoup.select.Elements#lastIndexOf": 884,
    "org.jsoup.select.Elements#listIterator": 884,
    "org.jsoup.select.Elements#not": 884,
    "org.jsoup.select.Elements#outerHtml": 125,
    "org.jsoup.select.Elements#parents": 884,
    "org.jsoup.select.Elements#prepend": 884,
    "org.jsoup.select.Elements#remove": 884,
    "org.jsoup.select.Elements#removeAll": 884,
    "org.jsoup.select.Elements#removeAttr": 884,
    "org.jsoup.select.Elements#removeClass": 884,
    "org.jsoup.select.Elements#retainAll": 884,
    "org.jsoup.select.Elements#select": 884,
    "org.jsoup.select.Elements#set": 884,
    "org.jsoup.select.Elements#size": 344,
    "org.jsoup.select.Elements#subList": 884,
    "org.jsoup.select.Elements#tagName": 884,
    "org.jsoup.select.Elements#text": 332,
    "org.jsoup.select.Elements#toArray": 884,
    "org.jsoup.select.Elements#toString": 884,
    "org.jsoup.select.Elements#toggleClass": 884,
    "org.jsoup.select.Elements#traverse": 884,
    "org.jsoup.select.Elements#unwrap": 884,
    "org.jsoup.select.Elements#val": 884,
    "org.jsoup.select.Elements#wrap": 884,
    "org.jsoup.select.Evaluator#Evaluator": 295,
    "org.jsoup.select.Evaluator.AllElements#Evaluator$AllElements": 339,
    "org.jsoup.select.Evaluator.AllElements#matches": 339,
    "org.jsoup.select.Evaluator.AllElements#toString": 884,
    "org.jsoup.select.Evaluator.Attribute#Evaluator$Attribute": 108,
    "org.jsoup.select.Evaluator.Attribute#matches": 147,
    "org.jsoup.select.Evaluator.Attribute#toString": 884,
    "org.jsoup.select.Evaluator.AttributeKeyPair#Evaluator$AttributeKeyPair": 95,
    "org.jsoup.select.Evaluator.AttributeStarting#Evaluator$AttributeStarting": 884,
    "org.jsoup.select.Evaluator.AttributeStarting#matches": 884,
    "org.jsoup.select.Evaluator.AttributeStarting#toString": 884,
    "org.jsoup.select.Evaluator.AttributeWithValue#Evaluator$AttributeWithValue": 90,
    "org.jsoup.select.Evaluator.AttributeWithValue#matches": 86,
    "org.jsoup.select.Evaluator.AttributeWithValue#toString": 884,
    "org.jsoup.select.Evaluator.AttributeWithValueContaining#Evaluator$AttributeWithValueContaining": 298,
    "org.jsoup.select.Evaluator.AttributeWithValueContaining#matches": 298,
    "org.jsoup.select.Evaluator.AttributeWithValueContaining#toString": 884,
    "org.jsoup.select.Evaluator.AttributeWithValueEnding#Evaluator$AttributeWithValueEnding": 884,
    "org.jsoup.select.Evaluator.AttributeWithValueEnding#matches": 884,
    "org.jsoup.select.Evaluator.AttributeWithValueEnding#toString": 884,
    "org.jsoup.select.Evaluator.AttributeWithValueMatching#Evaluator$AttributeWithValueMatching": 884,
    "org.jsoup.select.Evaluator.AttributeWithValueMatching#matches": 884,
    "org.jsoup.select.Evaluator.AttributeWithValueMatching#toString": 884,
    "org.jsoup.select.Evaluator.AttributeWithValueNot#Evaluator$AttributeWithValueNot": 884,
    "org.jsoup.select.Evaluator.AttributeWithValueNot#matches": 884,
    "org.jsoup.select.Evaluator.AttributeWithValueNot#toString": 884,
    "org.jsoup.select.Evaluator.AttributeWithValueStarting#Evaluator$AttributeWithValueStarting": 884,
    "org.jsoup.select.Evaluator.AttributeWithValueStarting#matches": 884,
    "org.jsoup.select.Evaluator.AttributeWithValueStarting#toString": 884,
    "org.jsoup.select.Evaluator.Class#Evaluator$Class": 176,
    "org.jsoup.select.Evaluator.Class#matches": 174,
    "org.jsoup.select.Evaluator.Class#toString": 884,
    "org.jsoup.select.Evaluator.ContainsOwnText#Evaluator$ContainsOwnText": 884,
    "org.jsoup.select.Evaluator.ContainsOwnText#matches": 884,
    "org.jsoup.select.Evaluator.ContainsOwnText#toString": 884,
    "org.jsoup.select.Evaluator.ContainsText#Evaluator$ContainsText": 154,
    "org.jsoup.select.Evaluator.ContainsText#matches": 154,
    "org.jsoup.select.Evaluator.ContainsText#toString": 884,
    "org.jsoup.select.Evaluator.Id#Evaluator$Id": 346,
    "org.jsoup.select.Evaluator.Id#matches": 346,
    "org.jsoup.select.Evaluator.Id#toString": 884,
    "org.jsoup.select.Evaluator.IndexEquals#Evaluator$IndexEquals": 884,
    "org.jsoup.select.Evaluator.IndexEquals#matches": 884,
    "org.jsoup.select.Evaluator.IndexEquals#toString": 884,
    "org.jsoup.select.Evaluator.IndexEvaluator#Evaluator$IndexEvaluator": 884,
    "org.jsoup.select.Evaluator.IndexGreaterThan#Evaluator$IndexGreaterThan": 884,
    "org.jsoup.select.Evaluator.IndexGreaterThan#matches": 884,
    "org.jsoup.select.Evaluator.IndexGreaterThan#toString": 884,
    "org.jsoup.select.Evaluator.IndexLessThan#Evaluator$IndexLessThan": 884,
    "org.jsoup.select.Evaluator.IndexLessThan#matches": 884,
    "org.jsoup.select.Evaluator.IndexLessThan#toString": 884,
    "org.jsoup.select.Evaluator.Matches#Evaluator$Matches": 884,
    "org.jsoup.select.Evaluator.Matches#matches": 884,
    "org.jsoup.select.Evaluator.Matches#toString": 884,
    "org.jsoup.select.Evaluator.MatchesOwn#Evaluator$MatchesOwn": 884,
    "org.jsoup.select.Evaluator.MatchesOwn#matches": 884,
    "org.jsoup.select.Evaluator.MatchesOwn#toString": 884,
    "org.jsoup.select.Evaluator.Tag#Evaluator$Tag": 223,
    "org.jsoup.select.Evaluator.Tag#matches": 218,
    "org.jsoup.select.Evaluator.Tag#toString": 884,
    "org.jsoup.select.NodeTraversor#NodeTraversor": 323,
    "org.jsoup.select.NodeTraversor#traverse": 323,
    "org.jsoup.select.QueryParser#<clinit>": 215,
    "org.jsoup.select.QueryParser#QueryParser": 215,
    "org.jsoup.select.QueryParser#allElements": 332,
    "org.jsoup.select.QueryParser#byAttribute": 117,
    "org.jsoup.select.QueryParser#byClass": 174,
    "org.jsoup.select.QueryParser#byId": 343,
    "org.jsoup.select.QueryParser#byTag": 191,
    "org.jsoup.select.QueryParser#combinator": 110,
    "org.jsoup.select.QueryParser#consumeIndex": 884,
    "org.jsoup.select.QueryParser#consumeSubQuery": 110,
    "org.jsoup.select.QueryParser#contains": 169,
    "org.jsoup.select.QueryParser#findElements": 215,
    "org.jsoup.select.QueryParser#has": 884,
    "org.jsoup.select.QueryParser#indexEquals": 884,
    "org.jsoup.select.QueryParser#indexGreaterThan": 884,
    "org.jsoup.select.QueryParser#indexLessThan": 884,
    "org.jsoup.select.QueryParser#matches": 884,
    "org.jsoup.select.QueryParser#not": 884,
    "org.jsoup.select.QueryParser#parse": 129,
    "org.jsoup.select.Selector#Selector": 202,
    "org.jsoup.select.Selector#filterOut": 884,
    "org.jsoup.select.Selector#select": 202,
    "org.jsoup.select.StructuralEvaluator#StructuralEvaluator": 326,
    "org.jsoup.select.StructuralEvaluator.Has#StructuralEvaluator$Has": 884,
    "org.jsoup.select.StructuralEvaluator.Has#matches": 884,
    "org.jsoup.select.StructuralEvaluator.Has#toString": 884,
    "org.jsoup.select.StructuralEvaluator.ImmediateParent#StructuralEvaluator$ImmediateParent": 298,
    "org.jsoup.select.StructuralEvaluator.ImmediateParent#matches": 265,
    "org.jsoup.select.StructuralEvaluator.ImmediateParent#toString": 884,
    "org.jsoup.select.StructuralEvaluator.ImmediatePreviousSibling#StructuralEvaluator$ImmediatePreviousSibling": 884,
    "org.jsoup.select.StructuralEvaluator.ImmediatePreviousSibling#matches": 884,
    "org.jsoup.select.StructuralEvaluator.ImmediatePreviousSibling#toString": 884,
    "org.jsoup.select.StructuralEvaluator.Not#StructuralEvaluator$Not": 884,
    "org.jsoup.select.StructuralEvaluator.Not#matches": 884,
    "org.jsoup.select.StructuralEvaluator.Not#toString": 884,
    "org.jsoup.select.StructuralEvaluator.Parent#StructuralEvaluator$Parent": 342,
    "org.jsoup.select.StructuralEvaluator.Parent#matches": 336,
    "org.jsoup.select.StructuralEvaluator.Parent#toString": 884,
    "org.jsoup.select.StructuralEvaluator.PreviousSibling#StructuralEvaluator$PreviousSibling": 884,
    "org.jsoup.select.StructuralEvaluator.PreviousSibling#matches": 884,
    "org.jsoup.select.StructuralEvaluator.PreviousSibling#toString": 884,
    "org.jsoup.select.StructuralEvaluator.Root#StructuralEvaluator$Root": 884,
    "org.jsoup.select.StructuralEvaluator.Root#matches": 884
}